Workbook

Sheet GPay-UPI Summary
A1: GPay / UPI — Incoming & Outgoing, Date-wise by Account
A2: UPI-tagged transactions only (excludes NEFT/IMPS/EMI/cash-deposit/internal transfers, shown separately in the Category Totals tab). All figures pull live via SUMIFS from each account's raw sheet.
A4: Date | B4: TNS Traders (HDFC 7278) GPay In | C4: TNS Traders (HDFC 7278) GPay Out | D4: Nagarajan (HDFC 6393) GPay In | E4: Nagarajan (HDFC 6393) GPay Out | F4: Nagarajan (ICICI 0314) GPay In | G4: Nagarajan (ICICI 0314) GPay Out | H4: Total GPay In (all accounts)
A5: 2026-07-06 | B5: =SUMIFS('TNS-HDFC 7278'!E:E,'TNS-HDFC 7278'!A:A,A5,'TNS-HDFC 7278'!C:C,"UPI") -> 0 | C5: =SUMIFS('TNS-HDFC 7278'!D:D,'TNS-HDFC 7278'!A:A,A5,'TNS-HDFC 7278'!C:C,"UPI") -> 0 | D5: =SUMIFS('Nagarajan-HDFC 6393'!E:E,'Nagarajan-HDFC 6393'!A:A,A5,'Nagarajan-HDFC 6393'!C:C,"UPI") -> 28310 | E5: =SUMIFS('Nagarajan-HDFC 6393'!D:D,'Nagarajan-HDFC 6393'!A:A,A5,'Nagarajan-HDFC 6393'!C:C,"UPI") -> 0 | F5: =SUMIFS('Nagarajan-ICICI 0314'!E:E,'Nagarajan-ICICI 0314'!A:A,A5,'Nagarajan-ICICI 0314'!C:C,"UPI") -> 0 | G5: =SUMIFS('Nagarajan-ICICI 0314'!D:D,'Nagarajan-ICICI 0314'!A:A,A5,'Nagarajan-ICICI 0314'!C:C,"UPI") -> 1316 | H5: =B5+D5+F5 -> 28310
A6: 2026-07-07 | B6: =SUMIFS('TNS-HDFC 7278'!E:E,'TNS-HDFC 7278'!A:A,A6,'TNS-HDFC 7278'!C:C,"UPI") -> 0 | C6: =SUMIFS('TNS-HDFC 7278'!D:D,'TNS-HDFC 7278'!A:A,A6,'TNS-HDFC 7278'!C:C,"UPI") -> 0 | D6: =SUMIFS('Nagarajan-HDFC 6393'!E:E,'Nagarajan-HDFC 6393'!A:A,A6,'Nagarajan-HDFC 6393'!C:C,"UPI") -> 28440 | E6: =SUMIFS('Nagarajan-HDFC 6393'!D:D,'Nagarajan-HDFC 6393'!A:A,A6,'Nagarajan-HDFC 6393'!C:C,"UPI") -> 0 | F6: =SUMIFS('Nagarajan-ICICI 0314'!E:E,'Nagarajan-ICICI 0314'!A:A,A6,'Nagarajan-ICICI 0314'!C:C,"UPI") -> 0 | G6: =SUMIFS('Nagarajan-ICICI 0314'!D:D,'Nagarajan-ICICI 0314'!A:A,A6,'Nagarajan-ICICI 0314'!C:C,"UPI") -> 12220 | H6: =B6+D6+F6 -> 28440
A7: 2026-07-08 | B7: =SUMIFS('TNS-HDFC 7278'!E:E,'TNS-HDFC 7278'!A:A,A7,'TNS-HDFC 7278'!C:C,"UPI") -> 0 | C7: =SUMIFS('TNS-HDFC 7278'!D:D,'TNS-HDFC 7278'!A:A,A7,'TNS-HDFC 7278'!C:C,"UPI") -> 0 | D7: =SUMIFS('Nagarajan-HDFC 6393'!E:E,'Nagarajan-HDFC 6393'!A:A,A7,'Nagarajan-HDFC 6393'!C:C,"UPI") -> 920 | E7: =SUMIFS('Nagarajan-HDFC 6393'!D:D,'Nagarajan-HDFC 6393'!A:A,A7,'Nagarajan-HDFC 6393'!C:C,"UPI") -> 0 | F7: =SUMIFS('Nagarajan-ICICI 0314'!E:E,'Nagarajan-ICICI 0314'!A:A,A7,'Nagarajan-ICICI 0314'!C:C,"UPI") -> 0 | G7: =SUMIFS('Nagarajan-ICICI 0314'!D:D,'Nagarajan-ICICI 0314'!A:A,A7,'Nagarajan-ICICI 0314'!C:C,"UPI") -> 250 | H7: =B7+D7+F7 -> 920
A8: 2026-07-09 | B8: =SUMIFS('TNS-HDFC 7278'!E:E,'TNS-HDFC 7278'!A:A,A8,'TNS-HDFC 7278'!C:C,"UPI") -> 0 | C8: =SUMIFS('TNS-HDFC 7278'!D:D,'TNS-HDFC 7278'!A:A,A8,'TNS-HDFC 7278'!C:C,"UPI") -> 0 | D8: =SUMIFS('Nagarajan-HDFC 6393'!E:E,'Nagarajan-HDFC 6393'!A:A,A8,'Nagarajan-HDFC 6393'!C:C,"UPI") -> 0 | E8: =SUMIFS('Nagarajan-HDFC 6393'!D:D,'Nagarajan-HDFC 6393'!A:A,A8,'Nagarajan-HDFC 6393'!C:C,"UPI") -> 0 | F8: =SUMIFS('Nagarajan-ICICI 0314'!E:E,'Nagarajan-ICICI 0314'!A:A,A8,'Nagarajan-ICICI 0314'!C:C,"UPI") -> 0 | G8: =SUMIFS('Nagarajan-ICICI 0314'!D:D,'Nagarajan-ICICI 0314'!A:A,A8,'Nagarajan-ICICI 0314'!C:C,"UPI") -> 10900 | H8: =B8+D8+F8 -> 0
A9: 2026-07-10 | B9: =SUMIFS('TNS-HDFC 7278'!E:E,'TNS-HDFC 7278'!A:A,A9,'TNS-HDFC 7278'!C:C,"UPI") -> 0 | C9: =SUMIFS('TNS-HDFC 7278'!D:D,'TNS-HDFC 7278'!A:A,A9,'TNS-HDFC 7278'!C:C,"UPI") -> 0 | D9: =SUMIFS('Nagarajan-HDFC 6393'!E:E,'Nagarajan-HDFC 6393'!A:A,A9,'Nagarajan-HDFC 6393'!C:C,"UPI") -> 0 | E9: =SUMIFS('Nagarajan-HDFC 6393'!D:D,'Nagarajan-HDFC 6393'!A:A,A9,'Nagarajan-HDFC 6393'!C:C,"UPI") -> 0 | F9: =SUMIFS('Nagarajan-ICICI 0314'!E:E,'Nagarajan-ICICI 0314'!A:A,A9,'Nagarajan-ICICI 0314'!C:C,"UPI") -> 0 | G9: =SUMIFS('Nagarajan-ICICI 0314'!D:D,'Nagarajan-ICICI 0314'!A:A,A9,'Nagarajan-ICICI 0314'!C:C,"UPI") -> 10630 | H9: =B9+D9+F9 -> 0
A10: 2026-07-11 | B10: =SUMIFS('TNS-HDFC 7278'!E:E,'TNS-HDFC 7278'!A:A,A10,'TNS-HDFC 7278'!C:C,"UPI") -> 0 | C10: =SUMIFS('TNS-HDFC 7278'!D:D,'TNS-HDFC 7278'!A:A,A10,'TNS-HDFC 7278'!C:C,"UPI") -> 0 | D10: =SUMIFS('Nagarajan-HDFC 6393'!E:E,'Nagarajan-HDFC 6393'!A:A,A10,'Nagarajan-HDFC 6393'!C:C,"UPI") -> 220 | E10: =SUMIFS('Nagarajan-HDFC 6393'!D:D,'Nagarajan-HDFC 6393'!A:A,A10,'Nagarajan-HDFC 6393'!C:C,"UPI") -> 1500 | F10: =SUMIFS('Nagarajan-ICICI 0314'!E:E,'Nagarajan-ICICI 0314'!A:A,A10,'Nagarajan-ICICI 0314'!C:C,"UPI") -> 0 | G10: =SUMIFS('Nagarajan-ICICI 0314'!D:D,'Nagarajan-ICICI 0314'!A:A,A10,'Nagarajan-ICICI 0314'!C:C,"UPI") -> 70 | H10: =B10+D10+F10 -> 220
A11: 2026-07-12 | B11: =SUMIFS('TNS-HDFC 7278'!E:E,'TNS-HDFC 7278'!A:A,A11,'TNS-HDFC 7278'!C:C,"UPI") -> 0 | C11: =SUMIFS('TNS-HDFC 7278'!D:D,'TNS-HDFC 7278'!A:A,A11,'TNS-HDFC 7278'!C:C,"UPI") -> 0 | D11: =SUMIFS('Nagarajan-HDFC 6393'!E:E,'Nagarajan-HDFC 6393'!A:A,A11,'Nagarajan-HDFC 6393'!C:C,"UPI") -> 0 | E11: =SUMIFS('Nagarajan-HDFC 6393'!D:D,'Nagarajan-HDFC 6393'!A:A,A11,'Nagarajan-HDFC 6393'!C:C,"UPI") -> 0 | F11: =SUMIFS('Nagarajan-ICICI 0314'!E:E,'Nagarajan-ICICI 0314'!A:A,A11,'Nagarajan-ICICI 0314'!C:C,"UPI") -> 0 | G11: =SUMIFS('Nagarajan-ICICI 0314'!D:D,'Nagarajan-ICICI 0314'!A:A,A11,'Nagarajan-ICICI 0314'!C:C,"UPI") -> 236 | H11: =B11+D11+F11 -> 0
A12: 2026-07-13 | B12: =SUMIFS('TNS-HDFC 7278'!E:E,'TNS-HDFC 7278'!A:A,A12,'TNS-HDFC 7278'!C:C,"UPI") -> 0 | C12: =SUMIFS('TNS-HDFC 7278'!D:D,'TNS-HDFC 7278'!A:A,A12,'TNS-HDFC 7278'!C:C,"UPI") -> 0 | D12: =SUMIFS('Nagarajan-HDFC 6393'!E:E,'Nagarajan-HDFC 6393'!A:A,A12,'Nagarajan-HDFC 6393'!C:C,"UPI") -> 32500 | E12: =SUMIFS('Nagarajan-HDFC 6393'!D:D,'Nagarajan-HDFC 6393'!A:A,A12,'Nagarajan-HDFC 6393'!C:C,"UPI") -> 32500 | F12: =SUMIFS('Nagarajan-ICICI 0314'!E:E,'Nagarajan-ICICI 0314'!A:A,A12,'Nagarajan-ICICI 0314'!C:C,"UPI") -> 0 | G12: =SUMIFS('Nagarajan-ICICI 0314'!D:D,'Nagarajan-ICICI 0314'!A:A,A12,'Nagarajan-ICICI 0314'!C:C,"UPI") -> 190 | H12: =B12+D12+F12 -> 32500
A13: 2026-07-14 | B13: =SUMIFS('TNS-HDFC 7278'!E:E,'TNS-HDFC 7278'!A:A,A13,'TNS-HDFC 7278'!C:C,"UPI") -> 0 | C13: =SUMIFS('TNS-HDFC 7278'!D:D,'TNS-HDFC 7278'!A:A,A13,'TNS-HDFC 7278'!C:C,"UPI") -> 0 | D13: =SUMIFS('Nagarajan-HDFC 6393'!E:E,'Nagarajan-HDFC 6393'!A:A,A13,'Nagarajan-HDFC 6393'!C:C,"UPI") -> 2000 | E13: =SUMIFS('Nagarajan-HDFC 6393'!D:D,'Nagarajan-HDFC 6393'!A:A,A13,'Nagarajan-HDFC 6393'!C:C,"UPI") -> 1952 | F13: =SUMIFS('Nagarajan-ICICI 0314'!E:E,'Nagarajan-ICICI 0314'!A:A,A13,'Nagarajan-ICICI 0314'!C:C,"UPI") -> 0 | G13: =SUMIFS('Nagarajan-ICICI 0314'!D:D,'Nagarajan-ICICI 0314'!A:A,A13,'Nagarajan-ICICI 0314'!C:C,"UPI") -> 3250 | H13: =B13+D13+F13 -> 2000
A14: 2026-07-15 | B14: =SUMIFS('TNS-HDFC 7278'!E:E,'TNS-HDFC 7278'!A:A,A14,'TNS-HDFC 7278'!C:C,"UPI") -> 0 | C14: =SUMIFS('TNS-HDFC 7278'!D:D,'TNS-HDFC 7278'!A:A,A14,'TNS-HDFC 7278'!C:C,"UPI") -> 0 | D14: =SUMIFS('Nagarajan-HDFC 6393'!E:E,'Nagarajan-HDFC 6393'!A:A,A14,'Nagarajan-HDFC 6393'!C:C,"UPI") -> 0 | E14: =SUMIFS('Nagarajan-HDFC 6393'!D:D,'Nagarajan-HDFC 6393'!A:A,A14,'Nagarajan-HDFC 6393'!C:C,"UPI") -> 5180 | F14: =SUMIFS('Nagarajan-ICICI 0314'!E:E,'Nagarajan-ICICI 0314'!A:A,A14,'Nagarajan-ICICI 0314'!C:C,"UPI") -> 0 | G14: =SUMIFS('Nagarajan-ICICI 0314'!D:D,'Nagarajan-ICICI 0314'!A:A,A14,'Nagarajan-ICICI 0314'!C:C,"UPI") -> 0 | H14: =B14+D14+F14 -> 0
A15: 2026-07-16 | B15: =SUMIFS('TNS-HDFC 7278'!E:E,'TNS-HDFC 7278'!A:A,A15,'TNS-HDFC 7278'!C:C,"UPI") -> 0 | C15: =SUMIFS('TNS-HDFC 7278'!D:D,'TNS-HDFC 7278'!A:A,A15,'TNS-HDFC 7278'!C:C,"UPI") -> 0 | D15: =SUMIFS('Nagarajan-HDFC 6393'!E:E,'Nagarajan-HDFC 6393'!A:A,A15,'Nagarajan-HDFC 6393'!C:C,"UPI") -> 0 | E15: =SUMIFS('Nagarajan-HDFC 6393'!D:D,'Nagarajan-HDFC 6393'!A:A,A15,'Nagarajan-HDFC 6393'!C:C,"UPI") -> 4825 | F15: =SUMIFS('Nagarajan-ICICI 0314'!E:E,'Nagarajan-ICICI 0314'!A:A,A15,'Nagarajan-ICICI 0314'!C:C,"UPI") -> 0 | G15: =SUMIFS('Nagarajan-ICICI 0314'!D:D,'Nagarajan-ICICI 0314'!A:A,A15,'Nagarajan-ICICI 0314'!C:C,"UPI") -> 0 | H15: =B15+D15+F15 -> 0
A16: 2026-07-17 | B16: =SUMIFS('TNS-HDFC 7278'!E:E,'TNS-HDFC 7278'!A:A,A16,'TNS-HDFC 7278'!C:C,"UPI") -> 0 | C16: =SUMIFS('TNS-HDFC 7278'!D:D,'TNS-HDFC 7278'!A:A,A16,'TNS-HDFC 7278'!C:C,"UPI") -> 0 | D16: =SUMIFS('Nagarajan-HDFC 6393'!E:E,'Nagarajan-HDFC 6393'!A:A,A16,'Nagarajan-HDFC 6393'!C:C,"UPI") -> 1750 | E16: =SUMIFS('Nagarajan-HDFC 6393'!D:D,'Nagarajan-HDFC 6393'!A:A,A16,'Nagarajan-HDFC 6393'!C:C,"UPI") -> 1200 | F16: =SUMIFS('Nagarajan-ICICI 0314'!E:E,'Nagarajan-ICICI 0314'!A:A,A16,'Nagarajan-ICICI 0314'!C:C,"UPI") -> 0 | G16: =SUMIFS('Nagarajan-ICICI 0314'!D:D,'Nagarajan-ICICI 0314'!A:A,A16,'Nagarajan-ICICI 0314'!C:C,"UPI") -> 0 | H16: =B16+D16+F16 -> 1750
... A62: 2026-09-01 | B62: =SUMIFS('TNS-HDFC 7278'!E:E,'TNS-HDFC 7278'!A:A,A62,'TNS-HDFC 7278'!C:C,"UPI") -> 0 | C62: =SUMIFS('TNS-HDFC 7278'!D:D,'TNS-HDFC 7278'!A:A,A62,'TNS-HDFC 7278'!C:C,"UPI") -> 0 | D62: =SUMIFS('Nagarajan-HDFC 6393'!E:E,'Nagarajan-HDFC 6393'!A:A,A62,'Nagarajan-HDFC 6393'!C:C,"UPI") -> 0 | E62: =SUMIFS('Nagarajan-HDFC 6393'!D:D,'Nagarajan-HDFC 6393'!A:A,A62,'Nagarajan-HDFC 6393'!C:C,"UPI") -> 135 | F62: =SUMIFS('Nagarajan-ICICI 0314'!E:E,'Nagarajan-ICICI 0314'!A:A,A62,'Nagarajan-ICICI 0314'!C:C,"UPI") -> 0 | G62: =SUMIFS('Nagarajan-ICICI 0314'!D:D,'Nagarajan-ICICI 0314'!A:A,A62,'Nagarajan-ICICI 0314'!C:C,"UPI") -> 0 | H62: =B62+D62+F62 -> 0
A63: TOTAL | B63: =SUM(B5:B62) -> 124820 | C63: =SUM(C5:C62) -> 37989.8 | D63: =SUM(D5:D62) -> 144708 | E63: =SUM(E5:E62) -> 261889 | F63: =SUM(F5:F62) -> 1 | G63: =SUM(G5:G62) -> 310470.9 | H63: =SUM(H5:H62) -> 269529

Sheet Category Totals
A1: Transaction Category Totals by Account
A2: Every rupee in each statement, split by transaction type — confirms nothing was missed classifying UPI vs NEFT/IMPS/EMI/etc.
A4: TNS Traders (HDFC 7278)
A5: Category | B5: Withdrawal (₹) | C5: Deposit (₹) | D5: Count
A6: UPI | B6: =SUMIFS('TNS-HDFC 7278'!D:D,'TNS-HDFC 7278'!C:C,A6) -> 37989.8 | C6: =SUMIFS('TNS-HDFC 7278'!E:E,'TNS-HDFC 7278'!C:C,A6) -> 124820 | D6: =COUNTIF('TNS-HDFC 7278'!C:C,A6) -> 224
A7: NEFT | B7: =SUMIFS('TNS-HDFC 7278'!D:D,'TNS-HDFC 7278'!C:C,A7) -> 0 | C7: =SUMIFS('TNS-HDFC 7278'!E:E,'TNS-HDFC 7278'!C:C,A7) -> 0 | D7: =COUNTIF('TNS-HDFC 7278'!C:C,A7) -> 0
A8: IMPS | B8: =SUMIFS('TNS-HDFC 7278'!D:D,'TNS-HDFC 7278'!C:C,A8) -> 0 | C8: =SUMIFS('TNS-HDFC 7278'!E:E,'TNS-HDFC 7278'!C:C,A8) -> 0 | D8: =COUNTIF('TNS-HDFC 7278'!C:C,A8) -> 0
A9: EMI | B9: =SUMIFS('TNS-HDFC 7278'!D:D,'TNS-HDFC 7278'!C:C,A9) -> 0 | C9: =SUMIFS('TNS-HDFC 7278'!E:E,'TNS-HDFC 7278'!C:C,A9) -> 0 | D9: =COUNTIF('TNS-HDFC 7278'!C:C,A9) -> 0
A10: FT (internal transfer) | B10: =SUMIFS('TNS-HDFC 7278'!D:D,'TNS-HDFC 7278'!C:C,A10) -> 0 | C10: =SUMIFS('TNS-HDFC 7278'!E:E,'TNS-HDFC 7278'!C:C,A10) -> 50000 | D10: =COUNTIF('TNS-HDFC 7278'!C:C,A10) -> 1
A11: Cash Deposit | B11: =SUMIFS('TNS-HDFC 7278'!D:D,'TNS-HDFC 7278'!C:C,A11) -> 0 | C11: =SUMIFS('TNS-HDFC 7278'!E:E,'TNS-HDFC 7278'!C:C,A11) -> 0 | D11: =COUNTIF('TNS-HDFC 7278'!C:C,A11) -> 0
A12: Bill/Internet transfer | B12: =SUMIFS('TNS-HDFC 7278'!D:D,'TNS-HDFC 7278'!C:C,A12) -> 0 | C12: =SUMIFS('TNS-HDFC 7278'!E:E,'TNS-HDFC 7278'!C:C,A12) -> 0 | D12: =COUNTIF('TNS-HDFC 7278'!C:C,A12) -> 0
A13: Other | B13: =SUMIFS('TNS-HDFC 7278'!D:D,'TNS-HDFC 7278'!C:C,A13) -> 21.04 | C13: =SUMIFS('TNS-HDFC 7278'!E:E,'TNS-HDFC 7278'!C:C,A13) -> 0 | D13: =COUNTIF('TNS-HDFC 7278'!C:C,A13) -> 5
A14: Account Total | B14: =SUM(B6:B13) -> 38010.84 | C14: =SUM(C6:C13) -> 174820
A16: Nagarajan (HDFC 6393)
A17: Category | B17: Withdrawal (₹) | C17: Deposit (₹) | D17: Count
A18: UPI | B18: =SUMIFS('Nagarajan-HDFC 6393'!D:D,'Nagarajan-HDFC 6393'!C:C,A18) -> 261889 | C18: =SUMIFS('Nagarajan-HDFC 6393'!E:E,'Nagarajan-HDFC 6393'!C:C,A18) -> 144708 | D18: =COUNTIF('Nagarajan-HDFC 6393'!C:C,A18) -> 163
A19: NEFT | B19: =SUMIFS('Nagarajan-HDFC 6393'!D:D,'Nagarajan-HDFC 6393'!C:C,A19) -> 0 | C19: =SUMIFS('Nagarajan-HDFC 6393'!E:E,'Nagarajan-HDFC 6393'!C:C,A19) -> 80000 | D19: =COUNTIF('Nagarajan-HDFC 6393'!C:C,A19) -> 1
A20: IMPS | B20: =SUMIFS('Nagarajan-HDFC 6393'!D:D,'Nagarajan-HDFC 6393'!C:C,A20) -> 0 | C20: =SUMIFS('Nagarajan-HDFC 6393'!E:E,'Nagarajan-HDFC 6393'!C:C,A20) -> 60001 | D20: =COUNTIF('Nagarajan-HDFC 6393'!C:C,A20) -> 4
A21: EMI | B21: =SUMIFS('Nagarajan-HDFC 6393'!D:D,'Nagarajan-HDFC 6393'!C:C,A21) -> 39957 | C21: =SUMIFS('Nagarajan-HDFC 6393'!E:E,'Nagarajan-HDFC 6393'!C:C,A21) -> 13319 | D21: =COUNTIF('Nagarajan-HDFC 6393'!C:C,A21) -> 4
A22: FT (internal transfer) | B22: =SUMIFS('Nagarajan-HDFC 6393'!D:D,'Nagarajan-HDFC 6393'!C:C,A22) -> 50000 | C22: =SUMIFS('Nagarajan-HDFC 6393'!E:E,'Nagarajan-HDFC 6393'!C:C,A22) -> 0 | D22: =COUNTIF('Nagarajan-HDFC 6393'!C:C,A22) -> 1
A23: Cash Deposit | B23: =SUMIFS('Nagarajan-HDFC 6393'!D:D,'Nagarajan-HDFC 6393'!C:C,A23) -> 0 | C23: =SUMIFS('Nagarajan-HDFC 6393'!E:E,'Nagarajan-HDFC 6393'!C:C,A23) -> 0 | D23: =COUNTIF('Nagarajan-HDFC 6393'!C:C,A23) -> 0
A24: Bill/Internet transfer | B24: =SUMIFS('Nagarajan-HDFC 6393'!D:D,'Nagarajan-HDFC 6393'!C:C,A24) -> 0 | C24: =SUMIFS('Nagarajan-HDFC 6393'!E:E,'Nagarajan-HDFC 6393'!C:C,A24) -> 0 | D24: =COUNTIF('Nagarajan-HDFC 6393'!C:C,A24) -> 0
A25: Other | B25: =SUMIFS('Nagarajan-HDFC 6393'!D:D,'Nagarajan-HDFC 6393'!C:C,A25) -> 450 | C25: =SUMIFS('Nagarajan-HDFC 6393'!E:E,'Nagarajan-HDFC 6393'!C:C,A25) -> 36.45 | D25: =COUNTIF('Nagarajan-HDFC 6393'!C:C,A25) -> 2
A26: Account Total | B26: =SUM(B18:B25) -> 352296 | C26: =SUM(C18:C25) -> 298064.45
A28: Nagarajan (ICICI 0314)
A29: Category | B29: Withdrawal (₹) | C29: Deposit (₹) | D29: Count
A30: UPI | B30: =SUMIFS('Nagarajan-ICICI 0314'!D:D,'Nagarajan-ICICI 0314'!C:C,A30) -> 310470.9 | C30: =SUMIFS('Nagarajan-ICICI 0314'!E:E,'Nagarajan-ICICI 0314'!C:C,A30) -> 1 | D30: =COUNTIF('Nagarajan-ICICI 0314'!C:C,A30) -> 111
A31: NEFT | B31: =SUMIFS('Nagarajan-ICICI 0314'!D:D,'Nagarajan-ICICI 0314'!C:C,A31) -> 0 | C31: =SUMIFS('Nagarajan-ICICI 0314'!E:E,'Nagarajan-ICICI 0314'!C:C,A31) -> 263460 | D31: =COUNTIF('Nagarajan-ICICI 0314'!C:C,A31) -> 46
A32: IMPS | B32: =SUMIFS('Nagarajan-ICICI 0314'!D:D,'Nagarajan-ICICI 0314'!C:C,A32) -> 60001 | C32: =SUMIFS('Nagarajan-ICICI 0314'!E:E,'Nagarajan-ICICI 0314'!C:C,A32) -> 0 | D32: =COUNTIF('Nagarajan-ICICI 0314'!C:C,A32) -> 4
A33: EMI | B33: =SUMIFS('Nagarajan-ICICI 0314'!D:D,'Nagarajan-ICICI 0314'!C:C,A33) -> 0 | C33: =SUMIFS('Nagarajan-ICICI 0314'!E:E,'Nagarajan-ICICI 0314'!C:C,A33) -> 0 | D33: =COUNTIF('Nagarajan-ICICI 0314'!C:C,A33) -> 0
A34: FT (internal transfer) | B34: =SUMIFS('Nagarajan-ICICI 0314'!D:D,'Nagarajan-ICICI 0314'!C:C,A34) -> 0 | C34: =SUMIFS('Nagarajan-ICICI 0314'!E:E,'Nagarajan-ICICI 0314'!C:C,A34) -> 0 | D34: =COUNTIF('Nagarajan-ICICI 0314'!C:C,A34) -> 0
A35: Cash Deposit | B35: =SUMIFS('Nagarajan-ICICI 0314'!D:D,'Nagarajan-ICICI 0314'!C:C,A35) -> 0 | C35: =SUMIFS('Nagarajan-ICICI 0314'!E:E,'Nagarajan-ICICI 0314'!C:C,A35) -> 97000 | D35: =COUNTIF('Nagarajan-ICICI 0314'!C:C,A35) -> 3
A36: Bill/Internet transfer | B36: =SUMIFS('Nagarajan-ICICI 0314'!D:D,'Nagarajan-ICICI 0314'!C:C,A36) -> 80000 | C36: =SUMIFS('Nagarajan-ICICI 0314'!E:E,'Nagarajan-ICICI 0314'!C:C,A36) -> 0 | D36: =COUNTIF('Nagarajan-ICICI 0314'!C:C,A36) -> 1
A37: Other | B37: =SUMIFS('Nagarajan-ICICI 0314'!D:D,'Nagarajan-ICICI 0314'!C:C,A37) -> 0 | C37: =SUMIFS('Nagarajan-ICICI 0314'!E:E,'Nagarajan-ICICI 0314'!C:C,A37) -> 0 | D37: =COUNTIF('Nagarajan-ICICI 0314'!C:C,A37) -> 0
A38: Account Total | B38: =SUM(B30:B37) -> 450471.9 | C38: =SUM(C30:C37) -> 360461

Sheet Cash Reconciliation Notes
A1: Cash-in-Hand Discrepancy — Diagnostic Notes
A3: 1. What was verified with certainty
A5: All three bank statements were parsed programmatically (not by eye) from the PDF text layer. Every account's extracted Withdrawal and Deposit totals were checked against that statement's own printed summary line and match to the paisa:
A7: • TNS Traders (HDFC 7278): Debits ₹38,010.84 / Credits ₹1,74,820.00 — matches statement summary exactly.
A9: • Nagarajan (HDFC 6393): Debits ₹3,52,296.00 / Credits ₹2,98,064.45 — matches statement summary exactly.
A11: • Nagarajan (ICICI 0314): opening balance + deposits − withdrawals reproduces the statement's final closing balance (₹10.13) to the paisa.
A13: The "GPay-UPI Summary" and "Category Totals" tabs are the direct, fully-verified answer to "overall GPay expense amount & incoming amount, account-wise and date-wise."
A15: 2. The cash-in-hand number could not be reconciled from this session's data — here is exactly why
A17: The Poondu Ledger app's "Cash In Hand" dashboard tile is bound to a formula the app itself labels "Cash In Hand (LIQUID)" — its own on-screen note says it "Combines Cash + GPay." I pulled the live ledger data directly from the deployed app (same source it reads from) and recomputed that exact formula in Python line-for-line. Result: ₹8,31,396 — not the ₹12,18,047 you quoted. That is a ₹3,86,651 gap I cannot explain from data available in this session.
A19: This means the ₹12,18,047 figure either came from a browser tab that had not refreshed against the sheet since some recent entries/deletions were made, or from a different tile/moment than the one I recomputed. Before chasing the "true" gap any further, please hard-refresh the Poondu Ledger app and re-read the Cash In Hand tile — if it still reads ₹12,18,047 against a freshly-loaded page, tell me and I will re-derive the formula from the live page's own JS execution rather than from a static copy of index.html, in case the deployed code has drifted from the file I have on record.
A21: 3. The real architectural finding — true regardless of which of the two numbers above is right
A23: Every sale and expense in the ledger from July 2 through September 1 is flagged isCash:true, with exactly ONE exception (one ₹11,000 credit sale). That is not a coincidence — the Cash / GPay / Credit payment-mode split was only added to the app THIS session (Sept 2). Every entry made before today defaulted to isCash:true because that field did not meaningfully exist yet.
... A39: (c) I can build a one-time "bulk re-tag" screen in the app (list all isCash:true sales in a date range, let you flip individual ones to GPay in bulk) if manually editing each one in Google Sheets is too slow — say the word and I'll scope it.

Sheet Nagarajan Spend Aug1-31
A1: Nagarajan Personal Accounts - Spend Detail, Aug 1-16 vs Aug 17-31
A2: Covers both HDFC 6393 and ICICI 0314. "Spend" = Withdrawal column. Col H flags internal money movement (self-transfer between the two personal accounts, or capital sent to TNS Traders current a/c) - not real spend. Col I flags verified genuine shop/procurement purchases (AKJ Traders, Dhanalakshmi Poondu garlic supplier) - matched only where the supplier name is the FIRST word of the narration, to avoid a known trailing-text parsing artifact on ICICI rows.
A4: SUMMARY
A5: Window | B5: Total Spend | C5: Spend txns | D5: Internal transfers (excl.) | E5: Genuine shop/procurement spend | F5: Other/personal spend (remainder)
A6: W1: Aug 1-16 | B6: =SUMIF(A11:A179,A6,F11:F179) -> 203761 | C6: =COUNTIFS(A11:A179,A6,F11:F179,">0") -> 76 | D6: =SUMIFS(F11:F179,A11:A179,A6,H11:H179,"<>") -> 110000 | E6: =SUMIFS(F11:F179,A11:A179,A6,I11:I179,"<>") -> 19100 | F6: =B6-D6-E6 -> 74661
A7: W2: Aug 17-31 | B7: =SUMIF(A11:A179,A7,F11:F179) -> 54884.9 | C7: =COUNTIFS(A11:A179,A7,F11:F179,">0") -> 39 | D7: =SUMIFS(F11:F179,A11:A179,A7,H11:H179,"<>") -> 0 | E7: =SUMIFS(F11:F179,A11:A179,A7,I11:I179,"<>") -> 49315 | F7: =B7-D7-E7 -> 5569.9
A9: DETAIL (all transactions, both accounts)
A10: Window | B10: Date | C10: Account | D10: Category | E10: Narration | F10: Withdrawal (Spend) | G10: Deposit | H10: Internal / Not a real spend? | I10: Genuine shop purchase?
A11: W1: Aug 1-16 | B11: 2026-08-01 | C11: HDFC 6393 | D11: UPI | E11: UPI-AKJ TRADERS-NASSARAKJ786@OKAXIS-UTIB 0000477-127180727435-UPI | F11: 3600 | G11: 0 | I11: Yes - AKJ Traders (supplier)
A12: W1: Aug 1-16 | B12: 2026-08-01 | C12: HDFC 6393 | D12: UPI | E12: UPI-BADMAVATHI P-KAVIBHAVANA381@OKHDFCBA NK-CNRB0000033-127202893401-UPI | F12: 0 | G12: 320
A13: W1: Aug 1-16 | B13: 2026-08-01 | C13: HDFC 6393 | D13: UPI | E13: UPI-HARIRITHANYA M-MUTHUKUMARP14771-5@O KAXIS-UCBA0000030-621306091961-UPI | F13: 0 | G13: 1000
A14: W1: Aug 1-16 | B14: 2026-08-01 | C14: ICICI 0314 | D14: NEFT | E14: PhonePe Limited NEFT-YESAP62134270843-PhonePe Limited-F09 M22UYYZ10YB2URED-002261100000025- YESB0000001 PhonePe Limited | F14: 0 | G14: 2165
A15: W1: Aug 1-16 | B15: 2026-08-02 | C15: HDFC 6393 | D15: UPI | E15: UPI-FORSRE MUTHUKUMARAN-PAYTM-8802906@P TYS-YESB0PTMUPI-127253749648-UPI | F15: 200 | G15: 0
A16: W1: Aug 1-16 | B16: 2026-08-02 | C16: HDFC 6393 | D16: UPI | E16: UPI-MRSBASKAR-BASKAR3739@OKICICI-IDIB0 00T015-621476312407-TRANSPORT | F16: 5200 | G16: 0
A17: W1: Aug 1-16 | B17: 2026-08-02 | C17: ICICI 0314 | D17: NEFT | E17: PhonePe Limited NEFT-YESAP62144194966-PhonePe Limited-F09 M22UYYZ10YB2URED-002261100000025- YESB0000001 PhonePe Limited | F17: 0 | G17: 14295
A18: W1: Aug 1-16 | B18: 2026-08-03 | C18: HDFC 6393 | D18: UPI | E18: UPI-J UDAYAKUMAR-UDAYSON007@OKAXIS-UTIB0 001294-621586033782-UPI | F18: 0 | G18: 250
A19: W1: Aug 1-16 | B19: 2026-08-03 | C19: HDFC 6393 | D19: UPI | E19: UPI-SAVALARAM-PAYTMQR6MYBWG@PTYS-YESB0PT MUPI-127300151139-UPI HDFCBANKLIMITED *Closingbalanceincludesfundsearmarkedforholdandunclearedfunds Contentsofthisstatementwillbeconsideredcorrectifnoerrorisreportedwithin30daysofreceiptofstatement.TheaddressonthisstatementisthatonrecordwiththeBankasatthedayofrequesting thisstatement. StateaccountbranchGSTN:33AAACH2702H1Z7 HDFCBankGSTINnumberdetailsareavailableathttps://www.hdfcbank.com/personal/making-payments/online-tax-payment/goods-and-service-tax. RegisteredOfficeAddress:HDFCBankHouse,SenapatiBapatMarg,LowerParel,Mumbai400013 | F19: 400 | G19: 0
A20: W1: Aug 1-16 | B20: 2026-08-03 | C20: HDFC 6393 | D20: UPI | E20: UPI-MRMANIMARAN MUTHUSA-BHARATPE.9Q0U0B 0Y8Q580770@UNITYPE-SBIN0000990-127300844 945-PAYTOBHARATPEME | F20: 30 | G20: 0
A21: W1: Aug 1-16 | B21: 2026-08-03 | C21: HDFC 6393 | D21: UPI | E21: UPI-SHAJAHAN IBRAHIM-9043533162@YBL-TMBL 0000059-030446898923-PAYMENTFROMPHONE | F21: 0 | G21: 1000
A22: W1: Aug 1-16 | B22: 2026-08-03 | C22: HDFC 6393 | D22: IMPS | E22: IMPS-621514265120-NAGARAJANT-ICIC-XXXXX XXX0314-IMPSTRANSACTION | F22: 0 | G22: 40000 | H22: Yes - self-transfer between own 2 accounts
A23: W1: Aug 1-16 | B23: 2026-08-03 | C23: HDFC 6393 | D23: UPI | E23: UPI-KALIAMMAL K-KALIYAMMALKALIYAMMAL510@ OKICICI-BKID0008201-658117462648-UPI | F23: 0 | G23: 1500
A24: W1: Aug 1-16 | B24: 2026-08-03 | C24: ICICI 0314 | D24: NEFT | E24: PhonePe Limited NEFT-YESAP62155029499-PhonePe Limited-F09 M22UYYZ10YB2URED-002261100000025- YESB0000001 NAGARAJAN | F24: 0 | G24: 8110
A25: W1: Aug 1-16 | B25: 2026-08-03 | C25: ICICI 0314 | D25: IMPS | E25: NAGARAJAN MMT/IMPS/621514265120/NAGARAJAN /HDFC0002231 PhonePe Limited | F25: 40000 | G25: 0 | H25: Yes - self-transfer between own 2 accounts
A26: W1: Aug 1-16 | B26: 2026-08-04 | C26: HDFC 6393 | D26: UPI | E26: UPI-CPMARUTHACHALAM AN-PAYTMQR6LT9FC@P TYS-YESB0PTMUPI-127343134719-UPI | F26: 200 | G26: 0
A27: W1: Aug 1-16 | B27: 2026-08-04 | C27: HDFC 6393 | D27: UPI | E27: UPI-NASSARAKJ786OKAXIS-NASSARAKJ786@OKAX IS-UTIB0000477-658218532149-UPI | F27: 8600 | G27: 0
A28: W1: Aug 1-16 | B28: 2026-08-04 | C28: HDFC 6393 | D28: UPI | E28: UPI-JSYED RABIYAMMAL-SHAFIYASHAFIYA686@ OKSBI-TNSC0011700-658278475714-UPI | F28: 3000 | G28: 0
A29: W1: Aug 1-16 | B29: 2026-08-04 | C29: HDFC 6393 | D29: UPI | E29: UPI-CPMARUTHACHALAM AN-PAYTMQR6LT9ES@P TYS-YESB0PTMUPI-127384649320-UPI | F29: 200 | G29: 0
A30: W1: Aug 1-16 | B30: 2026-08-04 | C30: ICICI 0314 | D30: NEFT | E30: PhonePe Limited NEFT-YESAP62164484795-PhonePe Limited-F09 M22UYYZ10YB2URED-002261100000025- YESB0000001 PhonePe Limited | F30: 0 | G30: 2635
A31: W1: Aug 1-16 | B31: 2026-08-05 | C31: HDFC 6393 | D31: UPI | E31: UPI-SURESHLESSISHOP3-Q844887125@YBL-Y ESB0YBLUPI-127412677917-UPI | F31: 50 | G31: 0
A32: W1: Aug 1-16 | B32: 2026-08-05 | C32: HDFC 6393 | D32: UPI | E32: UPI-KRISHS NAIR-KRISHSNAIR1@OKHDFCBANK- FDRL0001288-127438812736-GST | F32: 500 | G32: 0
A33: W1: Aug 1-16 | B33: 2026-08-05 | C33: HDFC 6393 | D33: UPI | E33: UPI-SARAVANANS M-SMSARAVANANSMSARAVANAN 2@OKICICI-CNRB0000033-658341668011-UPI | F33: 0 | G33: 130
A34: W1: Aug 1-16 | B34: 2026-08-05 | C34: ICICI 0314 | D34: NEFT | E34: PhonePe Limited NEFT-YESAP62174096931-PhonePe Limited-F09 M22UYYZ10YB2URED-002261100000025- YESB0000001 PhonePe Limited | F34: 0 | G34: 1700
A35: W1: Aug 1-16 | B35: 2026-08-06 | C35: HDFC 6393 | D35: UPI | E35: UPI-POPULARBAKESAND HDFCBANKLIMITED *Closingbalanceincludesfundsearmarkedforholdandunclearedfunds Contentsofthisstatementwillbeconsideredcorrectifnoerrorisreportedwithin30daysofreceiptofstatement.TheaddressonthisstatementisthatonrecordwiththeBankasatthedayofrequesting thisstatement. StateaccountbranchGSTN:33AAACH2702H1Z7 HDFCBankGSTINnumberdetailsareavailableathttps://www.hdfcbank.com/personal/making-payments/online-tax-payment/goods-and-service-tax. RegisteredOfficeAddress:HDFCBankHouse,SenapatiBapatMarg,LowerParel,Mumbai400013 | F35: 20 | G35: 0
A36: W1: Aug 1-16 | B36: 2026-08-06 | C36: HDFC 6393 | D36: IMPS | E36: IMPS-621811855692-NAGARAJANT-ICIC-XXXXX XXX0314-IMPSTRANSACTION | F36: 0 | G36: 10000 | H36: Yes - self-transfer between own 2 accounts
A37: W1: Aug 1-16 | B37: 2026-08-06 | C37: HDFC 6393 | D37: UPI | E37: UPI-NASSARAKJ786OKAXIS-NASSARAKJ786@OKAX IS-UTIB0000477-658492352651-UPI | F37: 3600 | G37: 0
A38: W1: Aug 1-16 | B38: 2026-08-06 | C38: HDFC 6393 | D38: FT (internal transfer) | E38: FT-DR-50200120147278-TNSTRADERS | F38: 50000 | G38: 0 | H38: Yes - to TNS Traders (capital, not spend)
A39: W1: Aug 1-16 | B39: 2026-08-06 | C39: HDFC 6393 | D39: UPI | E39: UPI-DHILSATH M-PAYTM.S281AHM@PTY-YESB0MC HUPI-127494779858-UPI | F39: 30 | G39: 0
A40: W1: Aug 1-16 | B40: 2026-08-06 | C40: ICICI 0314 | D40: NEFT | E40: PhonePe Limited NEFT-YESAP62184577325-PhonePe Limited-F09 M22UYYZ10YB2URED-002261100000025- YESB0000001 NAGARAJAN | F40: 0 | G40: 3802
A41: W1: Aug 1-16 | B41: 2026-08-06 | C41: ICICI 0314 | D41: IMPS | E41: NAGARAJAN MMT/IMPS/621811855692/NAGARAJAN /HDFC0002231 PhonePe Limited | F41: 10000 | G41: 0 | H41: Yes - self-transfer between own 2 accounts
A42: W1: Aug 1-16 | B42: 2026-08-07 | C42: HDFC 6393 | D42: UPI | E42: UPI-CPMARUTHACHALAM AN-PAYTMQR6LT9F6@P TYS-YESB0PTMUPI-127504623150-UPI | F42: 100 | G42: 0
A43: W1: Aug 1-16 | B43: 2026-08-07 | C43: HDFC 6393 | D43: UPI | E43: UPI-HARIRITHANYA M-MUTHUKUMARP14771-5@O KAXIS-UCBA0000030-621997349027-UPI | F43: 0 | G43: 4000
A44: W1: Aug 1-16 | B44: 2026-08-07 | C44: HDFC 6393 | D44: EMI | E44: EMI467832485CHQS46783248500510826467 832485 | F44: 13319 | G44: 0
A45: W1: Aug 1-16 | B45: 2026-08-07 | C45: HDFC 6393 | D45: EMI | E45: EMI467832485CHQS46783248500510826467 832485 | F45: 0 | G45: 13319
A46: W1: Aug 1-16 | B46: 2026-08-07 | C46: HDFC 6393 | D46: IMPS | E46: IMPS-621915603998-NAGARAJANT-ICIC-XXXXX XXX0314-IMPSTRANSACTION | F46: 0 | G46: 10000 | H46: Yes - self-transfer between own 2 accounts
A47: W1: Aug 1-16 | B47: 2026-08-07 | C47: ICICI 0314 | D47: NEFT | E47: PhonePe Limited NEFT-YESAP62194008020-PhonePe Limited-F09 M22UYYZ10YB2URED-002261100000025- YESB0000001 AKJ TRADER | F47: 0 | G47: 10860
A48: W1: Aug 1-16 | B48: 2026-08-07 | C48: ICICI 0314 | D48: UPI | E48: AKJ TRADER UPI/AKJ TRADER/nassarakj786@o/UPI/AXIS BANK/621909981754/ICIc72923a6b7c5457db43ad b71d02953ad/ NAGARAJAN | F48: 3600 | G48: 0 | I48: Yes - AKJ Traders (supplier)
A49: W1: Aug 1-16 | B49: 2026-08-07 | C49: ICICI 0314 | D49: IMPS | E49: NAGARAJAN MMT/IMPS/621915603998/NAGARAJAN /HDFC0002231 Ramesh M | F49: 10000 | G49: 0 | H49: Yes - self-transfer between own 2 accounts
A50: W1: Aug 1-16 | B50: 2026-08-07 | C50: ICICI 0314 | D50: UPI | E50: Ramesh M UPI/Ramesh M/paytm.s2epecl@/UPI/YES BANK P/658586324243/ICI707f274c66f445ac9ecb5f7d5d 936d09/ Vishwa Mut | F50: 140 | G50: 0
A51: W1: Aug 1-16 | B51: 2026-08-07 | C51: ICICI 0314 | D51: UPI | E51: Vishwa Mut UPI/Vishwa Mut/q661096482@ybl/UPI/YES BANK L/658579408665/ICIea8571d687234cdd8a14c0f6b 42be79e/ Vishwa Mut | F51: 225 | G51: 0
A52: W1: Aug 1-16 | B52: 2026-08-07 | C52: ICICI 0314 | D52: UPI | E52: Vishwa Mut UPI/Vishwa Mut/q661096482@ybl/UPI/YES BANK L/658528629956/ICI0f2f9d9bdae84b59b2ab2ccc4a bc502d/ PhonePe Limited | F52: 20 | G52: 0
A53: W1: Aug 1-16 | B53: 2026-08-08 | C53: HDFC 6393 | D53: EMI | E53: EMI467832485CHQS46783248500510826467 832485-467832485 | F53: 13319 | G53: 0
A54: W1: Aug 1-16 | B54: 2026-08-08 | C54: HDFC 6393 | D54: UPI | E54: UPI-SHAJAHAN IBRAHIM-9043533162@YBL-TMBL 0000059-278693714287-PAYMENTFROMPHONE | F54: 0 | G54: 1860
A55: W1: Aug 1-16 | B55: 2026-08-08 | C55: HDFC 6393 | D55: UPI | E55: UPI-KANNAN-9597602921@AXL-IOBA0002671-16 6627795474-PAYMENTFROMPHONE | F55: 0 | G55: 180
A56: W1: Aug 1-16 | B56: 2026-08-08 | C56: ICICI 0314 | D56: NEFT | E56: PhonePe Limited NEFT-YESAP62204220465-PhonePe Limited-F09 M22UYYZ10YB2URED-002261100000025- YESB0000001 Noor Hasan | F56: 0 | G56: 3847
A57: W1: Aug 1-16 | B57: 2026-08-08 | C57: ICICI 0314 | D57: UPI | E57: Noor Hasan UPI/Noor Hasan/paytm.s1ll34j@/UPI/YES BANK P/658607433675/ICI19b5c8f7df144b62830604172 e1316e4/ www.icici.bank.in Dial your Bank 1800-1080 Please call from your registered mobile number for faster access Never share your OTP, CVV or passwords with anyone, even if the person claims to be a Bank employee. | F57: 30 | G57: 0
A58: W1: Aug 1-16 | B58: 2026-08-08 | C58: ICICI 0314 | D58: UPI | E58: Suganya A UPI/Suganya A/paytm.s225qiv@/UPI/YES BANK P/658605832663/ICIbf966ef3ea034e3cb87f873253 32ce1f/ sriidharv | F58: 30 | G58: 0
A59: W1: Aug 1-16 | B59: 2026-08-08 | C59: ICICI 0314 | D59: UPI | E59: sriidharv UPI/sriidharv/sriidharv@okic/UPI/ICICI Bank/658692466671/ICI03520d5d51a64f18b7870d 661208f0aa/ NEW ANNAPO | F59: 50 | G59: 0
A60: W1: Aug 1-16 | B60: 2026-08-08 | C60: ICICI 0314 | D60: UPI | E60: NEW ANNAPO UPI/NEW ANNAPO/q132905451@ybl/UPI/YES BANK L/658650975973/ICIe975f315658f4937b81773f417 7cb164/ MANIMARAN | F60: 60 | G60: 0
A61: W1: Aug 1-16 | B61: 2026-08-08 | C61: ICICI 0314 | D61: UPI | E61: MANIMARAN UPI/MANIMARAN/paytmqr6do4pc@/UPI/YES BANK L/658615067263/ICI5f9fdb419ff14fc5a6669e143d9 a0da7/ KATHIRVEL | F61: 30 | G61: 0
... A112: W1: Aug 1-16 | B112: 2026-08-15 | C112: ICICI 0314 | D112: NEFT | E112: PhonePe Limited NEFT-YESAP62275442510-PhonePe Limited-F09 M22UYYZ10YB2URED-002261100000025- YESB0000001 AKJ TRADER | F112: 0 | G112: 635
A113: W1: Aug 1-16 | B113: 2026-08-15 | C113: ICICI 0314 | D113: UPI | E113: AKJ TRADER UPI/AKJ TRADER/nassarakj786@o/ginger/AXIS BANK/659337941253/ICId6b32e056b7546daaeddb fc66f8f4335/ NEW ANNAPO | F113: 11900 | G113: 0 | I113: Yes - AKJ Traders (supplier)
A114: W1: Aug 1-16 | B114: 2026-08-15 | C114: ICICI 0314 | D114: UPI | E114: NEW ANNAPO UPI/NEW ANNAPO/q132905451@ybl/UPI/YES BANK L/659377939532/ICId6ace29c87df473385addaf7fc 11615a/ PhonePe Limited | F114: 140 | G114: 0
A115: W1: Aug 1-16 | B115: 2026-08-16 | C115: HDFC 6393 | D115: UPI | E115: UPI-PPRABHU PALANISWAMY-PRABHUPALANISAM Y2013@OKICICI-ICIC0001367-622848757229-U PI | F115: 0 | G115: 1537
A116: W1: Aug 1-16 | B116: 2026-08-16 | C116: ICICI 0314 | D116: NEFT | E116: PhonePe Limited NEFT-YESAP62285002502-PhonePe Limited-F09 M22UYYZ10YB2URED-002261100000025- YESB0000001 shankarpar | F116: 0 | G116: 15360
A117: W1: Aug 1-16 | B117: 2026-08-16 | C117: ICICI 0314 | D117: UPI | E117: shankarpar UPI/shankarpar/shankarparamu1/UPI/State Bank/659432397174/ICI9d1d9defafcd4466a343a9 3e7e5da4f8/ SRI SAI SR | F117: 500 | G117: 0
A118: W1: Aug 1-16 | B118: 2026-08-16 | C118: ICICI 0314 | D118: UPI | E118: SRI SAI SR UPI/SRI SAI SR/q280072661@ybl/UPI/YES BANK L/659425898567/ICI1c0f8ec43aa54974a6d46a198 22ad57e/ AROMA BAKE | F118: 60 | G118: 0
A119: W1: Aug 1-16 | B119: 2026-08-16 | C119: ICICI 0314 | D119: UPI | E119: AROMA BAKE UPI/AROMA BAKE/q318439692@ybl/UPI/YES BANK L/622838064464/ICIebff64091a514ab8836f70521b f3b4b9/ SRI BALAAJ | F119: 20 | G119: 0
A120: W1: Aug 1-16 | B120: 2026-08-16 | C120: ICICI 0314 | D120: UPI | E120: SRI BALAAJ UPI/SRI BALAAJ/paytm.s1ipzdm@/UPI/YES BANK P/622861962658/ICI8e899aeb18614f1dbdc024ce4 68ed4e1/ mthendrala | F120: 20 | G120: 0
A121: W1: Aug 1-16 | B121: 2026-08-16 | C121: ICICI 0314 | D121: UPI | E121: mthendrala UPI/mthendrala/mthendralarasu/rent balan/ICICI Bank/622855088994/ICI0c835311a2144ee58b22cf 386f1b8c92 Mr Sudhaka | F121: 8700 | G121: 0
A122: W1: Aug 1-16 | B122: 2026-08-16 | C122: ICICI 0314 | D122: UPI | E122: Mr Sudhaka UPI/Mr Sudhaka/suthakarann699/UPI/CITY UNION/622801385516/ICI21aba6953d5342e0a861 dbd2df1665a7/ PhonePe Limited | F122: 750 | G122: 0
A123: W2: Aug 17-31 | B123: 2026-08-17 | C123: HDFC 6393 | D123: UPI | E123: UPI-J DHARMASEELAN-DJSSEELI48@OKAXIS-TMB L0000335-659533689520-UPI | F123: 0 | G123: 240
A124: W2: Aug 17-31 | B124: 2026-08-17 | C124: ICICI 0314 | D124: NEFT | E124: PhonePe Limited NEFT-YESAP62295323133-PhonePe Limited-F09 M22UYYZ10YB2URED-002261100000025- YESB0000001 JAILABUDEE | F124: 0 | G124: 3935
A125: W2: Aug 17-31 | B125: 2026-08-17 | C125: ICICI 0314 | D125: UPI | E125: JAILABUDEE UPI/JAILABUDEE/paytmqr6q26w1@/UPI/YES BANK L/659535803583/ICId896c91e73f54190b5430ed85 b166041/ Sri Lakshm | F125: 30 | G125: 0
... A135: W2: Aug 17-31 | B135: 2026-08-18 | C135: ICICI 0314 | D135: UPI | E135: Mr KARTHIK UPI/Mr KARTHIK/paytm.s1ykans@/UPI/YES BANK P/659631643340/ICI32994993c931496786f495e94 c4e179f/ DHANALAKSH | F135: 30 | G135: 0
A136: W2: Aug 17-31 | B136: 2026-08-18 | C136: ICICI 0314 | D136: UPI | E136: DHANALAKSH UPI/DHANALAKSH/upi. 9600606293/dhanalaksh/South Indi/659617259066/ICI39fc7dfc2561491687a44cea 7ffd5510 C P Maruth | F136: 9240 | G136: 0 | I136: Yes - Dhanalakshmi Poondu (garlic supplier)
A137: W2: Aug 17-31 | B137: 2026-08-18 | C137: ICICI 0314 | D137: UPI | E137: C P Maruth UPI/C P Maruth/paytmqr6lt9et@/UPI/YES BANK L/659616855105/ICI7008009db42641ea90ae0f3a6 e15ed4f/ Noor Hasan | F137: 300 | G137: 0
A138: W2: Aug 17-31 | B138: 2026-08-18 | C138: ICICI 0314 | D138: UPI | E138: Noor Hasan UPI/Noor Hasan/paytm.s1ll34j@/UPI/YES BANK P/659603376199/ICIfa0d870202f1437d83ef563fd2 672f54/ R RAMESH | F138: 30 | G138: 0
A139: W2: Aug 17-31 | B139: 2026-08-18 | C139: ICICI 0314 | D139: UPI | E139: R RAMESH UPI/R RAMESH/bharatpe9o0j7j/Pay to Bha/YesBank_Ye/659611776890/ICI50761ed6211a 4e3893e6aac7f24aad32/ Google Ind | F139: 75 | G139: 0
A140: W2: Aug 17-31 | B140: 2026-08-18 | C140: ICICI 0314 | D140: UPI | E140: Google Ind UPI/Google Ind/gpayrecharge@o/UPI/AXIS BANK/659640181080/ICI1bfc244433834465af352d ffc91ee3e2/ KRISHNAA M | F140: 300.9 | G140: 0
A141: W2: Aug 17-31 | B141: 2026-08-18 | C141: ICICI 0314 | D141: UPI | E141: KRISHNAA M UPI/KRISHNAA M/krishnaamedica/UPI/State Bank/659642487433/ICIfb459a44f3314e13b30b15 0ec08a3c3e/ govindaraj | F141: 25 | G141: 0
A142: W2: Aug 17-31 | B142: 2026-08-18 | C142: ICICI 0314 | D142: UPI | E142: govindaraj UPI/govindaraj/govindarajrang/UPI/TAMILNAD M/659649896563/ICI237e35c778d747d9a6568bc6 0f0c8597/ PhonePe Limited | F142: 80 | G142: 0
A143: W2: Aug 17-31 | B143: 2026-08-19 | C143: HDFC 6393 | D143: UPI | E143: UPI-AKJ TRADERS-NASSARAKJ786@OKAXIS-UTIB 0000477-128155993315-UPI | F143: 8400 | G143: 0 | I143: Yes - AKJ Traders (supplier)
A144: W2: Aug 17-31 | B144: 2026-08-19 | C144: HDFC 6393 | D144: UPI | E144: UPI-DRMANOHARAN HOSPITA-VYAPAR.17569287 9512@HDFCBANK-HDFC0MERUPI-128158350020-U HDFCBANKLIMITED *Closingbalanceincludesfundsearmarkedforholdandunclearedfunds Contentsofthisstatementwillbeconsideredcorrectifnoerrorisreportedwithin30daysofreceiptofstatement.TheaddressonthisstatementisthatonrecordwiththeBankasatthedayofrequesting thisstatement. StateaccountbranchGSTN:33AAACH2702H1Z7 HDFCBankGSTINnumberdetailsareavailableathttps://www.hdfcbank.com/personal/making-payments/online-tax-payment/goods-and-service-tax. RegisteredOfficeAddress:HDFCBankHouse,SenapatiBapatMarg,LowerParel,Mumbai400013 | F144: 200 | G144: 0
A145: W2: Aug 17-31 | B145: 2026-08-19 | C145: HDFC 6393 | D145: UPI | E145: UPI-DRMANOHARAN HOSPITA-VYAPAR.17569287 9512@HDFCBANK-HDFC0MERUPI-128162930699-U PI | F145: 170 | G145: 0
A146: W2: Aug 17-31 | B146: 2026-08-19 | C146: ICICI 0314 | D146: NEFT | E146: PhonePe Limited NEFT-YESAP62315472837-PhonePe Limited-F09 M22UYYZ10YB2URED-002261100000025- YESB0000001 Mr KARTHIK | F146: 0 | G146: 2240
A147: W2: Aug 17-31 | B147: 2026-08-19 | C147: ICICI 0314 | D147: UPI | E147: Mr KARTHIK UPI/Mr KARTHIK/paytm.s1ykans@/UPI/YES BANK P/623188941137/ICI8470976343014bdcb990e48c6 291719b/ www.icici.bank.in Dial your Bank 1800-1080 Please call from your registered mobile number for faster access Never share your OTP, CVV or passwords with anyone, even if the person claims to be a Bank employee. | F147: 50 | G147: 0
A148: W2: Aug 17-31 | B148: 2026-08-19 | C148: ICICI 0314 | D148: UPI | E148: NEW ANNAPO UPI/NEW ANNAPO/q132905451@ybl/UPI/YES BANK L/623108647074/ICI3b111b08cdea4e658a6f5bd0ff df9827/ SUFEENA P | F148: 110 | G148: 0
A149: W2: Aug 17-31 | B149: 2026-08-19 | C149: ICICI 0314 | D149: UPI | E149: SUFEENA P UPI/SUFEENA P/7025713257@axl/cash/CANARA BAN/623168765193/ICI0722f09f09b04f7782d8536 1ecbec1d1/ DHANALAKSH | F149: 390 | G149: 0
A150: W2: Aug 17-31 | B150: 2026-08-19 | C150: ICICI 0314 | D150: UPI | E150: DHANALAKSH UPI/DHANALAKSH/upi.9600606293/UPI/South Indi/623193850173/ICI48c08016e01f40dbb2c0eecc 95b0c7d2/ PhonePe Limited | F150: 9240 | G150: 0 | I150: Yes - Dhanalakshmi Poondu (garlic supplier)
A151: W2: Aug 17-31 | B151: 2026-08-20 | C151: HDFC 6393 | D151: UPI | E151: UPI-DRMANOHARAN HOSPITA-VYAPAR.17569287 9512@HDFCBANK-HDFC0MERUPI-128197066192-U PI | F151: 1200 | G151: 0
A152: W2: Aug 17-31 | B152: 2026-08-20 | C152: HDFC 6393 | D152: UPI | E152: UPI-MR KARTHIKEYAN R-PAYTM.S1YKANS@PTY -YESB0MCHUPI-128197638928-UPI | F152: 30 | G152: 0
A153: W2: Aug 17-31 | B153: 2026-08-20 | C153: HDFC 6393 | D153: UPI | E153: UPI-DRMANOHARAN HOSPITA-VYAPAR.17569287 9512@HDFCBANK-HDFC0MERUPI-128208050722-U PI | F153: 114 | G153: 0
A154: W2: Aug 17-31 | B154: 2026-08-20 | C154: HDFC 6393 | D154: UPI | E154: UPI-MRUDHAYAKUMAR G-UDHAYKUMAR1022@OKS BI-CIUB0000129-128209015091-GAS | F154: 1000 | G154: 0
A155: W2: Aug 17-31 | B155: 2026-08-20 | C155: HDFC 6393 | D155: UPI | E155: UPI-HOTELCHEAPANDBEST-PAYTM.D71037727 @PTY-YESB0MCHUPI-128216271425-UPI | F155: 160 | G155: 0
A156: W2: Aug 17-31 | B156: 2026-08-20 | C156: ICICI 0314 | D156: NEFT | E156: PhonePe Limited NEFT-YESAP62325422583-PhonePe Limited-F09 M22UYYZ10YB2URED-002261100000025- YESB0000001 PhonePe Limited | F156: 0 | G156: 3100
A157: W2: Aug 17-31 | B157: 2026-08-21 | C157: HDFC 6393 | D157: UPI | E157: UPI-PONMANIGNANABAI J-PAYTM.S2VVZGI@PTY -YESB0MCHUPI-128249950190-UPI | F157: 30 | G157: 0
A158: W2: Aug 17-31 | B158: 2026-08-21 | C158: HDFC 6393 | D158: UPI | E158: UPI-MRSSARITHAVENI R-KAVYAMURALI81488 @OKICICI-CBIN0281418-623379651571-UPI | F158: 0 | G158: 1300
A159: W2: Aug 17-31 | B159: 2026-08-21 | C159: HDFC 6393 | D159: UPI | E159: UPI-AKJ TRADERS-Q867462875@YBL-YESB0YBLU PI-128282100780-GINGER | F159: 3400 | G159: 0 | I159: Yes - AKJ Traders (supplier)
A160: W2: Aug 17-31 | B160: 2026-08-21 | C160: HDFC 6393 | D160: UPI | E160: UPI-SHANKAR T-SHANKARPARAMU1993@OKICICI HDFCBANKLIMITED *Closingbalanceincludesfundsearmarkedforholdandunclearedfunds Contentsofthisstatementwillbeconsideredcorrectifnoerrorisreportedwithin30daysofreceiptofstatement.TheaddressonthisstatementisthatonrecordwiththeBankasatthedayofrequesting thisstatement. StateaccountbranchGSTN:33AAACH2702H1Z7 HDFCBankGSTINnumberdetailsareavailableathttps://www.hdfcbank.com/personal/making-payments/online-tax-payment/goods-and-service-tax. RegisteredOfficeAddress:HDFCBankHouse,SenapatiBapatMarg,LowerParel,Mumbai400013 | F160: 100 | G160: 0
A161: W2: Aug 17-31 | B161: 2026-08-21 | C161: ICICI 0314 | D161: NEFT | E161: PhonePe Limited NEFT-YESAP62335600589-PhonePe Limited-F09 M22UYYZ10YB2URED-002261100000025- YESB0000001 PhonePe Limited | F161: 0 | G161: 2100
...

Sheet TNS-HDFC 7278
A1: TNS Traders (HDFC 7278) — All Transactions
A2: Extracted programmatically from the bank-provided PDF statement. Verified: sum of Withdrawal/Deposit columns matches the statement's own summary totals exactly.
A4: Date | B4: Narration | C4: Category | D4: Withdrawal (₹) | E4: Deposit (₹) | F4: Balance (₹)
A5: 2026-08-06 | B5: FT-CR-50100072796393-NAGARAJANT | C5: FT (internal transfer) | E5: 50000 | F5: 50000
A6: 2026-08-11 | B6: UPISETTLEMENT-KES170-11/08/26 | C6: UPI | E6: 221 | F6: 50221
A7: 2026-08-15 | B7: UPISETTLEMENT-KES170-15/08/26 | C7: UPI | E7: 2600 | F7: 52821
A8: 2026-08-16 | B8: UPISETTLEMENT-KES170-16/08/26 | C8: UPI | E8: 360 | F8: 53181
A9: 2026-08-17 | B9: UPISETTLEMENT-KES170-17/08/26 | C9: UPI | E9: 3080 | F9: 56261
A10: 2026-08-18 | B10: UPISETTLEMENT-KES170-18/08/26 | C10: UPI | E10: 60 | F10: 56321
A11: 2026-08-19 | B11: UPISETTLEMENT-KES170-19/08/26 | C11: UPI | E11: 1095 | F11: 57416
A12: 2026-08-22 | B12: UPI-6897690963-DIVINESTARK111-2@OKICICI- 623436673528-UPI | C12: UPI | E12: 160 | F12: 57576
A13: 2026-08-22 | B13: UPI-916010046088863-SUREGARAJENDREN19@OK AXIS-623482505878-GARLIC | C13: UPI | E13: 235 | F13: 57811
A14: 2026-08-22 | B14: UPI-420150050800546-JAYATHANAM381@OKHDFC BANK-128302479729-UPI | C14: UPI | E14: 6300 | F14: 64111
A15: 2026-08-22 | B15: UPI-201021214733-9444203807@SUPERYES-623 420165407-PAIDVIASUPERMONEYUPI | C15: UPI | E15: 1160 | F15: 65271
A16: 2026-08-22 | B16: UPI-571910110004008-R.SHANMUKARAJA456-1@ OKHDFCBANK-128302805488-UPI | C16: UPI | E16: 290 | F16: 65561
... A58: 2026-08-24 | B58: UPI-170001000006229-NEELAVENI2204S@OKICI CI-623695066633-UPI | C58: UPI | E58: 500 | F58: 77191
A59: 2026-08-24 | B59: UPI-MRSHEMALATHA G-HEMAJANANIMSC-1@OKIC ICI-IDIB000R023-623659530405-UPI | C59: UPI | D59: 1 | F59: 77190
A60: 2026-08-24 | B60: UPI-AROMABAKERY NRS-Q318439692@YBL-YES B0YBLUPI-623650876912-UPISENDMONEY | C60: UPI | D60: 40 | F60: 77150
A61: 2026-08-24 | B61: UPI-115237828006-SAGEEB4U@OKHDFCBANK-128 426350581-UPI | C61: UPI | E61: 100 | F61: 77250
A62: 2026-08-24 | B62: UPI-VINOTHA KANNAIYAN-PAYTM.S2SMF3E@PTY- YESB0MCHUPI-128427188737-UPI | C62: UPI | D62: 50 | F62: 77200
A63: 2026-08-24 | B63: UPI-BOOMIRAJ T-BOOMI10MSP@OKICICI-SBIN0 016317-623600134363-UPI | C63: UPI | D63: 140 | F63: 77060
A64: 2026-08-24 | B64: UPI-053401000035032-7540042931@YBL-95610 9853560-PAYMENTFROMPHONEPE | C64: UPI | E64: 110 | F64: 77170
A65: 2026-08-24 | B65: UPI-1232101071071-SELLAPPANPALANISWAMI19 51@OKICICI-623669564220-UPI | C65: UPI | E65: 120 | F65: 77290
A66: 2026-08-24 | B66: UPI-00000067230099420-AMANULLA7217@OKSBI -623647241010-UPI | C66: UPI | E66: 180 | F66: 77470
A67: 2026-08-24 | B67: UPI-865987263-MAILME.RUBYV-3@OKICICI-623 672877153-UPI | C67: UPI | E67: 170 | F67: 77640
A68: 2026-08-24 | B68: UPI-65301800000021147648-9361823460@PTYE S-214002238410-SENTUSINGPAYTMUPI HDFCBANKLIMITED *Closingbalanceincludesfundsearmarkedforholdandunclearedfunds Contentsofthisstatementwillb | C68: UPI | E68: 90 | F68: 77730
A69: 2026-08-24 | B69: UPI-00000039069626292-BALAKRISHNANKISHOR E1984-1@OKICICI-623659894785-UPI | C69: UPI | E69: 80 | F69: 77810
A70: 2026-08-24 | B70: UPI-61542250010328-BRINDHAPAVAL85@OKAXIS -623618858820-UPI | C70: UPI | E70: 220 | F70: 78030
A71: 2026-08-24 | B71: UPI-820610110017417-SURENDRANSHANMUGAM2@ OKAXIS-623642680516-UPI | C71: UPI | E71: 500 | F71: 78530
A72: 2026-08-24 | B72: UPI-6818980282-GRANGARAJ11@OKAXIS-623696 873176-UPI | C72: UPI | E72: 250 | F72: 78780
A73: 2026-08-25 | B73: UPI-00000030584912598-SHERIFFKMS-1@OKSBI -623767881819-GINGER | C73: UPI | E73: 260 | F73: 79040
A74: 2026-08-25 | B74: UPI-SUGANYA A-PAYTM.S225QIV@PTY-YESB0MCH UPI-128464594652-UPI | C74: UPI | D74: 50 | F74: 78990
A75: 2026-08-25 | B75: UPI-3556108000222-PMKAVI1989-3@OKHDFCBAN K-128469493990-UPI | C75: UPI | E75: 160 | F75: 79150
A76: 2026-08-25 | B76: UPI-7473342015-BHAVYAS.2207-2@OKHDFCBANK -128469741040-UPI | C76: UPI | E76: 80 | F76: 79230
A77: 2026-08-25 | B77: UPI-00000037900981145-SANTHANAKUMAR67881 @OKSBI-623778097426-UPI | C77: UPI | E77: 150 | F77: 79380
A78: 2026-08-25 | B78: UPI-041901000117659-9994477574@YESCRED-6 60321163502-PAIDVIACRED | C78: UPI | E78: 90 | F78: 79470
A79: 2026-08-25 | B79: UPI-75280100006202-VASANTHIARUL9496-2@OK AXIS-660376725788-UPI | C79: UPI | E79: 160 | F79: 79630
A80: 2026-08-25 | B80: UPI-JAGADESHT M-JAGADESHTM155@OKAXIS-KV BL0001739-660313230153-UPI | C80: UPI | E80: 5200 | F80: 84830
A81: 2026-08-25 | B81: UPI-53220004822812-BALAKRISHNANSASI1971- 5@OKICICI-660364929826-UPI | C81: UPI | E81: 200 | F81: 85030
A82: 2026-08-25 | B82: UPI-1326119002962-SUJATHAD945@OKAXIS-660 385707811-UPI | C82: UPI | E82: 80 | F82: 85110
A83: 2026-08-25 | B83: UPI-824810110000271-MONICAIRUDHAYARAJ-1@ OKAXIS-660397529801-UPI HDFCBANKLIMITED *Closingbalanceincludesfundsearmarkedforholdandunclearedfunds Contentsofthisstatementwillbeconsider | C83: UPI | E83: 80 | F83: 85190
A84: 2026-08-25 | B84: UPI-397100050302302-9962729232@YBL-00771 7696007-PAYMENTFROMPHONEPE | C84: UPI | E84: 80 | F84: 85270
A85: 2026-08-25 | B85: UPI-7344107748-SHANTHOSHVIJAY87@OKICICI- 660378530398-UPI | C85: UPI | E85: 250 | F85: 85520
A86: 2026-08-25 | B86: UPI-710081007-ARUMUGAMGOLD26-2@OKHDFCBAN K-128481042130-UPI | C86: UPI | E86: 240 | F86: 85760
... A92: 2026-08-25 | B92: UPI-059100050316464-9751479234@SUPERYES- 623769567371-PAIDVIASUPERMONEYUPI | C92: UPI | E92: 450 | F92: 87070
A93: 2026-08-25 | B93: 36882960RUPAYMDRRCVRY-25/08/26 | C93: Other | D93: 1.23 | F93: 87068.77
A94: 2026-08-25 | B94: UPI-99980114521110-SATISHEPYO@OKAXIS-660 317564827-T | C94: UPI | E94: 30 | F94: 87098.77
A95: 2026-08-25 | B95: UPI-00000032794353578-KALMADAM.SREEKUTTY @OKSBI-623702554194-UPI | C95: UPI | E95: 50 | F95: 87148.77
A96: 2026-08-25 | B96: UPI-65290200006529025003321920-SUDHAJAY3 5-4@OKAXIS-660374251965-UPI | C96: UPI | E96: 180 | F96: 87328.77
A97: 2026-08-25 | B97: UPI-6383504007-KARIBILLAMONDAL805@OKHDFC BANK-128497638886-UPI | C97: UPI | E97: 160 | F97: 87488.77
A98: 2026-08-25 | B98: UPI-7263311176-SRIRAMTAD-2@OKAXIS-660387 874181-UPI | C98: UPI | E98: 320 | F98: 87808.77
A99: 2026-08-25 | B99: UPI-00000030011053424-PREETHI2614-1@OKSB I-623712878670-UPI | C99: UPI | E99: 50 | F99: 87858.77
A100: 2026-08-25 | B100: UPI-65300300006530034091811500-STARJAHIR HDFCBANKLIMITED *Closingbalanceincludesfundsearmarkedforholdandunclearedfunds Contentsofthisstatementwillbeconsideredcorrectifnoerrorisrepo | C100: UPI | E100: 80 | F100: 87938.77
A101: 2026-08-25 | B101: UPI-0019053000032229-YASMINBEGUM23487@OK ICICI-660369555538-UPI | C101: UPI | E101: 160 | F101: 88098.77
A102: 2026-08-25 | B102: UPI-00000032112439943-NOBELRAJUSHA@OKSBI -623717824726-UPI | C102: UPI | E102: 100 | F102: 88198.77
A103: 2026-08-25 | B103: UPI-22100005733703-9585024171-2@AXL-6797 55010810-PAYMENTFROMPHONEPE | C103: UPI | E103: 1330 | F103: 89528.77
A104: 2026-08-26 | B104: UPI-50200112740799-SANMASS8888-4@OKHDFCB ANK-128518493593-UPI | C104: UPI | E104: 180 | F104: 89708.77
A105: 2026-08-26 | B105: UPI-EURONETSERVICES IND-GPAYRECHARGE2@O KPAYAXIS-UTIB0000553-623827006661-UPI | C105: UPI | D105: 200.9 | F105: 89507.87
A106: 2026-08-26 | B106: UPI-CPMARUTHACHALAM AN-PAYTMQR6LT9ES@P TYS-YESB0PTMUPI-128520610145-UPI | C106: UPI | D106: 400 | F106: 89107.87
A107: 2026-08-26 | B107: UPI-50231577391-9344234041@YBL-032189995 552-PAYMENTFROMPHONEPE | C107: UPI | E107: 55 | F107: 89162.87
A108: 2026-08-26 | B108: UPI-7004073407-VINUSREE189-1@OKAXIS-6238 34222689-UPI | C108: UPI | E108: 110 | F108: 89272.87
A109: 2026-08-26 | B109: UPI-DHANALAKSHMIPOONDU -UPI.9600606293@ SIB-SIBL0000019-128529690762-UPI | C109: UPI | D109: 4620 | F109: 84652.87
A110: 2026-08-26 | B110: UPI-65298900006588631182809692127-CSARJU N17-2@OKHDFCBANK-128532514610-UPI | C110: UPI | E110: 200 | F110: 84852.87
A111: 2026-08-26 | B111: 36882960RUPAYMDRRCVRY-26/08/26 | C111: Other | D111: 3.53 | F111: 84849.34
A112: 2026-08-26 | B112: UPI-536100050300340-MUTHUKUMARANMUTHUKUM ARAN818-1@OKHDFCBANK-128535850295-MALIGA I | C112: UPI | E112: 30 | F112: 84879.34
A113: 2026-08-26 | B113: UPI-185501000000144-RANGARAJAN9151@OKHDF CBANK-128538526569-UPI | C113: UPI | E113: 95 | F113: 84974.34
A114: 2026-08-26 | B114: UPI-58460100004378-DSFRUITSVEGETABLES@OK HDFCBANK-128540670922-UPI HDFCBANKLIMITED *Closingbalanceincludesfundsearmarkedforholdandunclearedfunds Contentsofthisstatementwillbeconsid | C114: UPI | E114: 930 | F114: 85904.34
A115: 2026-08-26 | B115: UPI-BIGTREE ENTERTAINMEN-BOOKMYSHOW@AXB- UTIB0000100-128541374620-UPI | C115: UPI | D115: 151.9 | F115: 85752.44
A116: 2026-08-26 | B116: UPI-05470100022310-9940860789@PTYES-6129 14286381-SENTUSINGPAYTMUPI | C116: UPI | E116: 120 | F116: 85872.44
A117: 2026-08-26 | B117: UPI-DHANUSH S-PAYTM.S1FWUNS@PTY-YESB0MCH UPI-128543836555-UPI | C117: UPI | D117: 40 | F117: 85832.44
A118: 2026-08-26 | B118: UPI-510909010236399-FAIZAL031982-1@OKHDF CBANK-128543948410-UPI | C118: UPI | E118: 160 | F118: 85992.44
A119: 2026-08-26 | B119: UPI-5550745326-6379921459@PTAXIS-6238778 97512-SENTUSINGPAYTMUPI | C119: UPI | E119: 130 | F119: 86122.44
A120: 2026-08-26 | B120: UPI-1392500102547101-RAIYAANSRZ2509@OKSB I-623864065861-UPI | C120: UPI | E120: 80 | F120: 86202.44
A121: 2026-08-27 | B121: UPI-916010075608838-SBABUCBE32@OKAXIS-62 3941080575-UPI | C121: UPI | E121: 280 | F121: 86482.44
A122: 2026-08-27 | B122: UPI-916010075608838-SBABUCBE32@OKAXIS-62 3953986441-UPI | C122: UPI | E122: 40 | F122: 86522.44
A123: 2026-08-27 | B123: UPI-PPRABHU PALANISWAMY-PRABHUPALANISAM Y2013@OKICICI-ICIC0001367-623975068648-U PI | C123: UPI | E123: 15120 | F123: 101642.44
A124: 2026-08-27 | B124: UPI-309007379400-MOHAMED.ZUNAITH@OKAXIS- 660580811460-UPI | C124: UPI | E124: 170 | F124: 101812.44
A125: 2026-08-27 | B125: UPI-335002010003272-GOWRIPRABHAKAR54-2@O KHDFCBANK-128573068079-UPI | C125: UPI | E125: 250 | F125: 102062.44
A126: 2026-08-27 | B126: UPI-0019073000005689-9952661940@SIB-1000 22986670-GARLIC | C126: UPI | E126: 320 | F126: 102382.44
A127: 2026-08-27 | B127: UPI-911010037331221-8248652791@SUPERYES- 623994028996-PAIDVIASUPERMONEYUPI | C127: UPI | E127: 60 | F127: 102442.44
A128: 2026-08-27 | B128: UPI-309801000005543-9842549628@PTYES-214 202255675-SENTUSINGPAYTMUPI HDFCBANKLIMITED *Closingbalanceincludesfundsearmarkedforholdandunclearedfunds Contentsofthisstatementwillbecons | C128: UPI | E128: 450 | F128: 102892.44
A129: 2026-08-27 | B129: UPI-P KARTHIKKUMAR-9944506012@IBL-SBIN 0010618-128579244406-SHOPAMT | C129: UPI | D129: 3000 | F129: 99892.44
A130: 2026-08-27 | B130: UPI-1248101563318-9597321677@SUPERYES-62 3995027675-PAIDVIASUPERMONEYUPI | C130: UPI | E130: 200 | F130: 100092.44
A131: 2026-08-27 | B131: UPI-49140100007490-SANDHIYAANBU1603@OKIC ICI-623939682292-UPI | C131: UPI | E131: 180 | F131: 100272.44
A132: 2026-08-27 | B132: UPI-65301800000007095392-9842514165@UPI- 145621963588-NOREMARK | C132: UPI | E132: 240 | F132: 100512.44
A133: 2026-08-27 | B133: UPI-P KARTHIK KUMAR-KARTHIKADVOCATE7@OK SBI-SBIN0010618-623907512628-TODAY | C133: UPI | E133: 8700 | F133: 109212.44
A134: 2026-08-27 | B134: UPI-147001000024672-DEVIPRIYANKANATARAJ4 11-2@OKICICI-623942489100-UPI | C134: UPI | E134: 50 | F134: 109262.44
A135: 2026-08-27 | B135: UPI-1205101143303-SUNITHAMALATHYBALAN@OK AXIS-660585055600-UPI | C135: UPI | E135: 70 | F135: 109332.44
A136: 2026-08-27 | B136: UPI-820518210004232-VISHNUKUMAR1999KRV@O KHDFCBANK-128601739404-UPI | C136: UPI | E136: 80 | F136: 109412.44
A137: 2026-08-27 | B137: UPI-00000031703159621-DEVIKAMRT123@OKSBI -623929159749-UPI | C137: UPI | E137: 80 | F137: 109492.44
A138: 2026-08-27 | B138: UPI-1326101028071-RANJITHABARANI.28@OKAX IS-660563366729-UPI | C138: UPI | E138: 1000 | F138: 110492.44
A139: 2026-08-27 | B139: 36882960RUPAYMDRRCVRY-27/08/26 | C139: Other | D139: 2.71 | F139: 110489.73
A140: 2026-08-28 | B140: UPI-00000067114124873-9495071757-2@YBL-4 13986850251-PAYMENTFROMPHONEPE | C140: UPI | E140: 180 | F140: 110669.73
A141: 2026-08-28 | B141: UPI-1253155000068298-M.SFAMILYMUTHU@OKAX IS-624078815436-UPI | C141: UPI | E141: 4410 | F141: 115079.73
A142: 2026-08-28 | B142: UPI-7135796949-THARANIADAH@OKAXIS-624068 707482-UPI | C142: UPI | E142: 110 | F142: 115189.73
A143: 2026-08-28 | B143: UPI-8903000100006937-RAJAPRIYAN945@OKHDF CBANK-128632849280-UPI | C143: UPI | E143: 2000 | F143: 117189.73
A144: 2026-08-28 | B144: UPI-SHANKAR T-SHANKARPARAMU1993@OKICICI HDFCBANKLIMITED *Closingbalanceincludesfundsearmarkedforholdandunclearedfunds Contentsofthisstatementwillbeconsideredcorrectifnoerrorisrepor | C144: UPI | D144: 500 | F144: 116689.73
A145: 2026-08-28 | B145: UPI-548902010014173-HONEYFRND1978@OKHDFC BANK-128642251380-UPI | C145: UPI | E145: 300 | F145: 116989.73
A146: 2026-08-28 | B146: UPI-608128422-SUPERAMANIAMDEVENDRA-1@OKI CICI-660691479815-UPI | C146: UPI | E146: 8100 | F146: 125089.73
A147: 2026-08-28 | B147: UPI-00000040264883611-BOOMIVBOOMINATHAN@ OKSBI-624075324549-UPI | C147: UPI | E147: 3250 | F147: 128339.73
...

Sheet Nagarajan-HDFC 6393
A1: Nagarajan (HDFC 6393) — All Transactions
A2: Extracted programmatically from the bank-provided PDF statement. Verified: sum of Withdrawal/Deposit columns matches the statement's own summary totals exactly.
A4: Date | B4: Narration | C4: Category | D4: Withdrawal (₹) | E4: Deposit (₹) | F4: Balance (₹)
A5: 2026-07-06 | B5: UPI-D SAMRAJ-SAMRAJD255@OKAXIS-INDB00000 21-618746266134-UPI | C5: UPI | E5: 800 | F5: 73776.25
A6: 2026-07-06 | B6: UPI-AJITHKUMAR S-AAJITHAJITH939@OKAXIS -IOBA0000124-618793157227-UPI | C6: UPI | E6: 2050 | F6: 75826.25
A7: 2026-07-06 | B7: UPI-RAJESH R-RAJESHPRIYAFEB04@OKSBI-SBI N0008608-618768853568-UPI | C7: UPI | E7: 4930 | F7: 80756.25
A8: 2026-07-06 | B8: UPI-ABDULMUTHALEP P-PS9605969@OKSBI-SBI N0001384-618772320001-UPI | C8: UPI | E8: 1950 | F8: 82706.25
A9: 2026-07-06 | B9: UPI-VMSVEGTABLES-8667811345@IOB-IOBA0 001747-618711905154-UPIFUNDTRANSFER | C9: UPI | E9: 18450 | F9: 101156.25
A10: 2026-07-06 | B10: UPI-DAISYRANI SUGUMAR-DAISYMANGUNI-3@OK ICICI-IOBA0001846-655324789784-UPI | C10: UPI | E10: 130 | F10: 101286.25
A11: 2026-07-07 | B11: UPI-VISHNUT M-VISHNUSHINCHAN@OKICICI-CN RB0000033-618805843360-UPI | C11: UPI | E11: 240 | F11: 101526.25
A12: 2026-07-07 | B12: EMI467832485CHQS46783248500410726467 832485 | C12: EMI | D12: 13319 | F12: 88207.25
A13: 2026-07-07 | B13: UPI-MRSUHAILAHAMED SIK-SHYSUHAIL@OKHDF CBANK-IDIB000K337-125921235237-UPI | C13: UPI | E13: 28200 | F13: 116407.25
A14: 2026-07-08 | B14: UPI-SMOHAN CO-M2037518@OKHDFCBANK-BARB0 VJMCOT-125931519920-UPI | C14: UPI | E14: 920 | F14: 117327.25
A15: 2026-07-11 | B15: UPI-SIVA SUBRAMANIAN-SIVASUBARAMANIAN16@ OKAXIS-CNRB0000000-619266513202-UPI | C15: UPI | E15: 220 | F15: 117547.25
A16: 2026-07-11 | B16: UPI-MSME FILINGS-MSMEFILINGS@OKHDFCBANK- HDFCBANKLIMITED *Closingbalanceincludesfundsearmarkedforholdandunclearedfunds Contentsofthisstatementwillbeconsideredcorrectifnoerrorisrepo | C16: UPI | D16: 1500 | F16: 116047.25
A17: 2026-07-13 | B17: UPI-INDHUMATHI-8870300492-3@AXL-ESMF0001 266-122085661581-PAYMENTFROMPHONE | C17: UPI | E17: 29500 | F17: 145547.25
A18: 2026-07-13 | B18: UPI-INDHUMATHI-8870300492-3@AXL-ESMF0001 266-621101201024-PAYMENTFROMPHONE | C18: UPI | E18: 3000 | F18: 148547.25
A19: 2026-07-13 | B19: UPI-MRSHEMALATHA G-HEMAJANANIMSC-1@OKIC ICI-IDIB000R023-656065411805-AUTOSALEA MT | C19: UPI | D19: 29500 | F19: 119047.25
A20: 2026-07-13 | B20: UPI-MRSHEMALATHA G-HEMAJANANIMSC-1@OKIC ICI-IDIB000R023-656047219878-AUTOSALEA MT | C20: UPI | D20: 3000 | F20: 116047.25
A21: 2026-07-14 | B21: UPI-ARUNKUMAR S-ARUNSAI060393@OKSBI-SBI N0000827-656171197724-CASH | C21: UPI | D21: 1500 | F21: 114547.25
A22: 2026-07-14 | B22: UPI-RAMACHANDRAN-PAYTM.S284E8T@PTY-YESB0 MCHUPI-126270425223-UPI | C22: UPI | D22: 150 | F22: 114397.25
A23: 2026-07-14 | B23: UPI-KARUPPUSAMY K-Q317395531@YBL-YESB0Y BLUPI-126270723337-UPI | C23: UPI | D23: 32 | F23: 114365.25
A24: 2026-07-14 | B24: UPI-CPMARUTHACHALAM AN-PAYTMQR6LT9FC@P TYS-YESB0PTMUPI-126280411024-UPI | C24: UPI | D24: 200 | F24: 114165.25
A25: 2026-07-14 | B25: UPI-JSYED RABIYAMMAL-SHAFIYASHAFIYA686@ OKICICI-TNSC0011700-619556998083-UPI | C25: UPI | E25: 2000 | F25: 116165.25
A26: 2026-07-14 | B26: UPI-DHANASEKAR KUMAR-Q543106160@YBL-YESB 0YBLUPI-126301984995-UPI | C26: UPI | D26: 70 | F26: 116095.25
A27: 2026-07-15 | B27: UPI-B MANIMEGALA-CCMAB.RASIKA@OKSBI-IOBA HDFCBANKLIMITED *Closingbalanceincludesfundsearmarkedforholdandunclearedfunds Contentsofthisstatementwillbeconsideredcorrectifnoerrorisrepo | C27: UPI | D27: 30 | F27: 116065.25
A28: 2026-07-15 | B28: UPI-CHANDRAN CHINNASAMY-ERCHANDRAN82-1@O KICICI-IOBA0000727-126327531679-RICE | C28: UPI | D28: 1650 | F28: 114415.25
A29: 2026-07-15 | B29: UPI-POOJAHARINIM-POOJAHARINI1234@OKSBI -KKBK0008659-126343903272-SORRYKARENT | C29: UPI | D29: 3500 | F29: 110915.25
A30: 2026-07-16 | B30: UPI-SHRIVARITRADERS-GPAY-11240888700@O KBIZAXIS-UTIB0000553-126364227188-GARLIC | C30: UPI | D30: 4685 | F30: 106230.25
A31: 2026-07-16 | B31: UPI-NOOR HASAN-PAYTM.S1LL34J@PTY-YESB0MC HUPI-126392567627-UPI | C31: UPI | D31: 30 | F31: 106200.25
A32: 2026-07-16 | B32: UPI-KRISHNAVENI-Q133286890@YBL-YESB0YBLU PI-126401795446-UPI | C32: UPI | D32: 20 | F32: 106180.25
A33: 2026-07-16 | B33: UPI-CHELLADURAI KARUPPA-GPAY-1219126229 4@OKBIZAXIS-UTIB0000553-126402383438-UPI | C33: UPI | D33: 40 | F33: 106140.25
A34: 2026-07-16 | B34: UPI-M VELMURUGAN-Q141268266@YBL-YESB0YBL UPI-126407219351-UPI | C34: UPI | D34: 50 | F34: 106090.25
A35: 2026-07-17 | B35: UPI-ABRAR KHAN-KHAN71828@OKSBI-SBIN0002 548-656419257942-UPI | C35: UPI | D35: 900 | F35: 105190.25
A36: 2026-07-17 | B36: UPI-SASI K-SWARNAKANNAN1@OKAXIS-BKID0008 200-656488370971-UPI | C36: UPI | E36: 1500 | F36: 106690.25
A37: 2026-07-17 | B37: UPI-JAYANNA-Q444639315@YBL-YESB0YBLUPI-1 26436895307-UPI | C37: UPI | D37: 100 | F37: 106590.25
A38: 2026-07-17 | B38: UPI-CPMARUTHACHALAM AN-PAYTMQR6LT9ES@P TYS-YESB0PTMUPI-126437199218-UPI | C38: UPI | D38: 200 | F38: 106390.25
A39: 2026-07-17 | B39: UPI-DMALAIPANDI-8220654668@AXL-HDFC0000 269-983924652535-PAYMENTFROMPHONE | C39: UPI | E39: 250 | F39: 106640.25
A40: 2026-07-18 | B40: UPI-SHRIVARITRADERS-GPAY-11240888700@O HDFCBANKLIMITED *Closingbalanceincludesfundsearmarkedforholdandunclearedfunds Contentsofthisstatementwillbeconsideredcorrectifnoerrorisreport | C40: UPI | D40: 6734 | F40: 99906.25
A41: 2026-07-18 | B41: UPI-RAVIKUMAR R-RAVIALAKKADA@OKSBI-SBIN 0008626-619924841229-UPI | C41: UPI | D41: 20 | F41: 99886.25
A42: 2026-07-18 | B42: UPI-VIGNESHD-VIKKI.3193-11@OKICICI-IDFB 0040101-619932047416-UPI | C42: UPI | D42: 1000 | F42: 98886.25
A43: 2026-07-18 | B43: UPI-KANNAN GANESAN-Q733184149@YBL-YESB0Y BLUPI-126488680251-UPI | C43: UPI | D43: 160 | F43: 98726.25
A44: 2026-07-18 | B44: UPI-MRBASKAR VENKATACHA-BASKARVENKATACH ALAM786-1@OKAXIS-IDIB000R023-65658510115 4-UPI | C44: UPI | E44: 1 | F44: 98727.25
A45: 2026-07-18 | B45: UPI-MRBASKAR VENKATACHA-BASKARVENKATACH ALAM786-1@OKAXIS-IDIB000R023-65650762427 4-UPI | C45: UPI | E45: 800 | F45: 99527.25
A46: 2026-07-19 | B46: UPI-SHANMUGAM ALAGUMUTHU-PAYTMQR6URZ76@P TYS-YESB0PTMUPI-126540892186-UPI | C46: UPI | D46: 50 | F46: 99477.25
A47: 2026-07-19 | B47: UPI-VIJAYAGENCIES-PAYTM-8859426@PTYS-YE SB0PTMUPI-126541060634-UPI | C47: UPI | D47: 200 | F47: 99277.25
A48: 2026-07-19 | B48: UPI-AROMABAKERY KS-Q644929906@YBL-YESB 0YBLUPI-126541303527-UPI | C48: UPI | D48: 40 | F48: 99237.25
A49: 2026-07-19 | B49: UPI-MR SAKTHIVEL-SAKTHIVELS2656@OKAXIS-I DIB000R023-126556575497-UPI | C49: UPI | D49: 150 | F49: 99087.25
A50: 2026-07-19 | B50: UPI-ROYALCYCLE MART-9843155099-1@OKBIZA XIS-UTIB0000553-126559580067-SKATING HDFCBANKLIMITED *Closingbalanceincludesfundsearmarkedforholdandunclearedfunds Contentsofthisstatementwi | C50: UPI | D50: 1200 | F50: 97887.25
A51: 2026-07-19 | B51: UPI-KARUPPUSAMY K-Q317395531@YBL-YESB0Y BLUPI-126561179770-UPI | C51: UPI | D51: 40 | F51: 97847.25
A52: 2026-07-20 | B52: UPI-JEMISA-PAYTM.S2295WR@PTY-YESB0MCHUPI -126583812456-UPI | C52: UPI | D52: 200 | F52: 97647.25
A53: 2026-07-20 | B53: UPI-SASI K-SWARNAKANNAN1@OKAXIS-BKID0008 200-620161557996-UPI | C53: UPI | E53: 1000 | F53: 98647.25
A54: 2026-07-20 | B54: UPI-RAMESH M-PAYTM.S2EZYIG@PTY-YESB0MCHU PI-126612230399-UPI | C54: UPI | D54: 70 | F54: 98577.25
A55: 2026-07-20 | B55: UPI-DHANASEKAR KUMAR-9894957733@KOTAK811 -KKBK0008785-620198597714-CASH | C55: UPI | D55: 3000 | F55: 95577.25
A56: 2026-07-21 | B56: UPI-CPMARUTHACHALAM AN-PAYTMQR6LT9ET@P TYS-YESB0PTMUPI-126621141518-UPI | C56: UPI | D56: 200 | F56: 95377.25
A57: 2026-07-21 | B57: UPI-VIVEK S-VK.VIVEK.CBE-1@OKAXIS-UTIB0 001919-126624800738-GINGER | C57: UPI | D57: 8400 | F57: 86977.25
A58: 2026-07-21 | B58: UPI-SHENBAHA VALLIR-SHENBAHAVALLI1960@OK SBI-SIBL0000019-656855930963-RENT | C58: UPI | D58: 20000 | F58: 66977.25
A59: 2026-07-21 | B59: UPI-MRSHEMALATHA G-HEMAJANANIMSC-1@OKIC ICI-IDIB000R023-126638486886-DEPOSITE | C59: UPI | D59: 31000 | F59: 35977.25
A60: 2026-07-21 | B60: UPI-MRSHEMALATHA G-HEMAJANANIMSC-1@OKIC ICI-IDIB000R023-126638883407-UPI | C60: UPI | D60: 500 | F60: 35477.25
A61: 2026-07-21 | B61: UPI-MRSHEMALATHA G-HEMAJANANIMSC-1@OKIC ICI-IDIB000R023-656817460676-UPI | C61: UPI | D61: 300 | F61: 35177.25
A62: 2026-07-21 | B62: UPI-SHANKAR HDFCBANKLIMITED *Closingbalanceincludesfundsearmarkedforholdandunclearedfunds Contentsofthisstatementwillbeconsideredcorrectifnoerrorisreportedwithin30daysofreceiptofst | C62: UPI | D62: 100 | F62: 35077.25
A63: 2026-07-21 | B63: UPI-MFRANCIS XAVIER-PAYTMQR6U4MJP@PTYS- YESB0PTMUPI-126662878479-UPI | C63: UPI | D63: 150 | F63: 34927.25
A64: 2026-07-22 | B64: UPI-Y PONMANI GNANABAI-Q935525351@YBL-Y ESB0YBLUPI-126669000836-UPI | C64: UPI | D64: 45 | F64: 34882.25
A65: 2026-07-22 | B65: UPI-SHANKAR T-SHANKARPARAMU1993@OKICICI -SBIN0003061-620307955139-UPI | C65: UPI | E65: 1 | F65: 34883.25
A66: 2026-07-22 | B66: UPI-DIVYAA A-PAYTM.S1YO9XZ@PTY-YESB0MCH UPI-126673401152-UPI | C66: UPI | D66: 20 | F66: 34863.25
A67: 2026-07-22 | B67: UPI-SURESH AGENCIES-PAYTM-9102086BOEG@PT YS-YESB0PTMUPI-126676568150-UPI | C67: UPI | D67: 200 | F67: 34663.25
A68: 2026-07-23 | B68: UPI-AIRTEL-AIRTELPAYMENTSB554262.RZP-TGL DRVYB9Q3BHP@RXAIRTEL-AIRP0000011-1267156 69034-PAYVIARAZORPAY | C68: UPI | D68: 1029 | F68: 33634.25
A69: 2026-07-23 | B69: UPI-SHANKAR T-SHANKARPARAMU1993@OKICICI -SBIN0003061-620474595541-UPI | C69: UPI | D69: 200 | F69: 33434.25
A70: 2026-07-23 | B70: UPI-JAYANNA-Q444639315@YBL-YESB0YBLUPI-1 26755301700-UPI | C70: UPI | D70: 125 | F70: 33309.25
A71: 2026-07-24 | B71: UPI-VIVEK S-VK.VIVEK.CBE-1@OKAXIS-UTIB0 001919-126769339633-GINGER | C71: UPI | D71: 8300 | F71: 25009.25
A72: 2026-07-24 | B72: UPI-LAKSHMANAN KANNAPPA-LAKSHMANLAKSHMA NAN13@OKHDFCBANK-CNRB0000033-12678402317 9-UPI | C72: UPI | D72: 90 | F72: 24919.25
A73: 2026-07-24 | B73: UPI-SHANKAR HDFCBANKLIMITED *Closingbalanceincludesfundsearmarkedforholdandunclearedfunds Contentsofthisstatementwillbeconsideredcorrectifnoerrorisreportedwithin30daysofreceiptofst | C73: UPI | D73: 500 | F73: 24419.25
A74: 2026-07-24 | B74: UPI-MR SIVACHANDRAN-SIVACHANDRANM777-1@O KICICI-IDIB000P016-620572864935-UPI | C74: UPI | D74: 100 | F74: 24319.25
A75: 2026-07-25 | B75: UPI-PRABU-PRABHUPRABHU00876@OKICICI-SBIN 0009588-620611396381-UPI | C75: UPI | D75: 250 | F75: 24069.25
A76: 2026-07-25 | B76: UPI-JIO-RELIANCERETAIL2.EASEBUZZ@KOTAKPA Y-KKBK0JPUPIA-126833933065-PAY | C76: UPI | D76: 11 | F76: 24058.25
A77: 2026-07-25 | B77: UPI-MRSHEMALATHA G-HEMAJANANIMSC-1@OKIC ICI-IDIB000R023-126834186911-UPI | C77: UPI | D77: 500 | F77: 23558.25
A78: 2026-07-25 | B78: UPI-PARIMALADEVIS-PARIDEVI03-1@OKICICI -BARB0VADAVA-657257929072-UPI | C78: UPI | E78: 500 | F78: 24058.25
A79: 2026-07-25 | B79: UPI-KALAISELVAN-KALAINITHYA.42021-1@OKAX IS-CNRB0000033-657268443499-UPI | C79: UPI | E79: 180 | F79: 24238.25
A80: 2026-07-25 | B80: UPI-MRANJESHSINGHPAL-Q212938143@YBL-Y ESB0YBLUPI-126859305728-UPI | C80: UPI | D80: 20 | F80: 24218.25
A81: 2026-07-26 | B81: UPI-MOHAMMEDALIKHAN S-MOHAMMEDALIKHAN5 72@OKICICI-SBIN0000990-657333870020-UPI | C81: UPI | E81: 10 | F81: 24228.25
A82: 2026-07-26 | B82: UPI-SASI K-SWARNAKANNAN1@OKAXIS-BKID0008 200-620774236713-UPI | C82: UPI | E82: 860 | F82: 25088.25
A83: 2026-07-26 | B83: UPI-CPMARUTHACHALAM AN-PAYTMQR6LT9ES@P TYS-YESB0PTMUPI-126891950587-UPI | C83: UPI | D83: 200 | F83: 24888.25
A84: 2026-07-26 | B84: UPI-MRSHEMALATHA G-HEMAJANANIMSC-1@OKIC ICI-IDIB000R023-620735525064-UPI | C84: UPI | D84: 50 | F84: 24838.25
A85: 2026-07-26 | B85: UPI-MUTHURAJA K-PAYTM.S1PBILM@PTY-YESB0M HDFCBANKLIMITED *Closingbalanceincludesfundsearmarkedforholdandunclearedfunds Contentsofthisstatementwillbeconsideredcorrectifnoerrorisrepo | C85: UPI | D85: 20 | F85: 24818.25
A86: 2026-07-26 | B86: UPI-SELVAM MUTHAIYA-PAYTM.S1J5UJU@PTY-YE SB0MCHUPI-126906075532-UPI | C86: UPI | D86: 180 | F86: 24638.25
A87: 2026-07-27 | B87: UPI-MURALIDHARAN POOJA-6369505924POOJA @KOTAK-KKBK0008659-126921304619-UPI | C87: UPI | D87: 3500 | F87: 21138.25
A88: 2026-07-27 | B88: UPI-AKJ TRADERS-NASSARAKJ786@OKAXIS-UTIB 0000477-126924103157-GINGER | C88: UPI | D88: 9300 | F88: 11838.25
A89: 2026-07-27 | B89: UPI-JAYANNA-Q444639315@YBL-YESB0YBLUPI-1 26962395476-UPI | C89: UPI | D89: 100 | F89: 11738.25
A90: 2026-07-28 | B90: UPI-AMUTHAVALLI S-Q858363630@YBL-YESB0YB LUPI-126972801670-UPI | C90: UPI | D90: 10 | F90: 11728.25
A91: 2026-07-28 | B91: UPI-NOOR HASAN-PAYTM.S1LL34J@PTY-YESB0MC HUPI-126974232456-UPI | C91: UPI | D91: 30 | F91: 11698.25
A92: 2026-07-28 | B92: UPI-MRAHAMADHUSAIN-7867001532-2@YBL-ID IB000M656-126974246916-UPI | C92: UPI | D92: 500 | F92: 11198.25
A93: 2026-07-28 | B93: UPI-SHAJAHAN IBRAHIM-9043533162@YBL-TMBL 0000059-677727167270-PAYMENTFROMPHONE | C93: UPI | E93: 1000 | F93: 12198.25
A94: 2026-07-28 | B94: IMPS-620918715347-NAGARAJANT-ICIC-XXXXX XXX0314-IMPSTRANSACTION | C94: IMPS | E94: 1 | F94: 12199.25
A95: 2026-07-28 | B95: NEFTCR-ICIC0SF0002-NAGARAJAN T-NAGARAJA NT-IN12620947986563 | C95: NEFT | E95: 80000 | F95: 92199.25
A96: 2026-07-28 | B96: UPI-VISHNU GARLIC-VISHNU01RAYAKVAL-1@OKH DFCBANK-HDFC0000470-620958169756-GARLIC PURCHASEMP | C96: UPI | D96: 57000 | F96: 35199.25
A97: 2026-07-28 | B97: UPI-AIRTEL-AIRTEL.PAYU@AXISBANK-UTIB0003 HDFCBANKLIMITED *Closingbalanceincludesfundsearmarkedforholdandunclearedfunds Contentsofthisstatementwillbeconsideredcorrectifnoerrorisrepo | C97: UPI | D97: 199 | F97: 35000.25
A98: 2026-07-28 | B98: UPI-THIYAGU SAKTHIVEL-PAYTM.S1DNZF7@PTY- YESB0MCHUPI-127012665963-UPI | C98: UPI | D98: 50 | F98: 34950.25
A99: 2026-07-29 | B99: UPI-DIVYAA A-PAYTM.S22AMAE@PTY-YESB0MCH UPI-127023859342-UPI | C99: UPI | D99: 20 | F99: 34930.25
A100: 2026-07-29 | B100: UPI-MADHAVAN N-GPAY-12203014690@OKBIZAXI S-UTIB0000553-127045001642-UPI | C100: UPI | D100: 80 | F100: 34850.25
A101: 2026-07-29 | B101: UPI-CHELLADURAI KARUPPA-GPAY-1126345485 7@OKBIZAXIS-UTIB0000553-127053812806-UPI | C101: UPI | D101: 35 | F101: 34815.25
...

Sheet Nagarajan-ICICI 0314
A1: Nagarajan (ICICI 0314) — All Transactions
A2: Extracted programmatically from the bank-provided PDF statement. Verified: sum of Withdrawal/Deposit columns matches the statement's own summary totals exactly.
A4: Date | B4: Narration | C4: Category | D4: Withdrawal (₹) | E4: Deposit (₹) | F4: Balance (₹)
A5: 2026-07-06 | B5: saravanaku UPI/saravanaku/saravanakumar3/UPI/CANARA BAN/655330876480/ICIcd5780aa5a0140dba80402 14696fd73a/ SASGHPL RA | C5: UPI | D5: 50 | F5: 89971.03
A6: 2026-07-06 | B6: SASGHPL RA UPI/SASGHPL RA/q816918291@ybl/UPI/YES BANK L/655341277129/ICIef5a9cf1e30c4f48a48afd078e5 dba97/ PhonePe Bu | C6: UPI | D6: 218 | F6: 89753.03
A7: 2026-07-06 | B7: PhonePe Bu UPI/PhonePe Bu/phonepedeviceo/Payment fo/YES BANK L/655328194249/ICI6a327044f4124bd3a6a4e4552 322e829 hemajanani | C7: UPI | D7: 318 | F7: 89435.03
A8: 2026-07-06 | B8: hemajanani UPI/hemajanani/hemajananimsc-/UPI/INDIAN BAN/618750506474/ICIb317ab7fc8454a4792cf689 572b6cf41/ DHANASEKAR | C8: UPI | D8: 700 | F8: 88735.03
A9: 2026-07-06 | B9: DHANASEKAR UPI/DHANASEKAR/q525652580@ybl/UPI/YES BANK L/618729638003/ICIbf2721d343374f328b9e89bad c1957f9/ PhonePe Limited | C9: UPI | D9: 30 | F9: 88705.03
A10: 2026-07-07 | B10: PhonePe Limited NEFT-YESAP61884990391-PhonePe Limited-F09 M22UYYZ10YB2URED-002261100000025- YESB0000001 C P Maruth | C10: NEFT | E10: 1190 | F10: 89895.03
A11: 2026-07-07 | B11: C P Maruth UPI/C P Maruth/paytmqr6lt9f6@/UPI/YES BANK L/618853645238/ICI5e22247e08534049b167bb5f5 b5e42c0/ COVAI PACK | C11: UPI | D11: 200 | F11: 89695.03
A12: 2026-07-07 | B12: COVAI PACK UPI/COVAI PACK/paytmqr6yv9kb@/shop cover/YES BANK L/618891745441/ICI18900bab66d64ff8bdf0add93b bd76c3 MANIMARAN | C12: UPI | D12: 60 | F12: 89635.03
A13: 2026-07-07 | B13: MANIMARAN UPI/MANIMARAN/maranmani29-4@/ginger/AXIS BANK/618848344981/ICIb5a81d8db73940cda1ef5 75a56a70884/ BALAPRAKAS | C13: UPI | D13: 11000 | F13: 78635.03
A14: 2026-07-07 | B14: BALAPRAKAS UPI/BALAPRAKAS/9361075590@ybl/maintenanc/C ANARA BAN/618892069762/ICI94b5574b96474d3d8e33f3 dcd114241c MADHAVAN N | C14: UPI | D14: 800 | F14: 77835.03
A15: 2026-07-07 | B15: MADHAVAN N UPI/MADHAVAN N/gpay-122007105/UPI/AXIS BANK/655471115650/ICI09d27e93f353415387bac 2bc2141775e/ www.icici.bank.in Dial your Bank 1800-1080 Please call from your registere | C15: UPI | D15: 40 | F15: 77795.03
A16: 2026-07-07 | B16: DHANASEKAR UPI/DHANASEKAR/q525652580@ybl/UPI/YES BANK L/655406501622/ICI3e7cae087fe24940bb9f8ae3a0 6694fa/ VINITHKUMA | C16: UPI | D16: 40 | F16: 77755.03
A17: 2026-07-07 | B17: VINITHKUMA UPI/VINITHKUMA/paytm.s28qr3f@/UPI/YES BANK P/655427011909/ICI001630c0aed24103bb5dff6f8c 35476d/ PhonePe Limited | C17: UPI | D17: 80 | F17: 77675.03
A18: 2026-07-08 | B18: PhonePe Limited NEFT-YESAP61894542483-PhonePe Limited-F09 M22UYYZ10YB2URED-002261100000025- YESB0000001 KATHIRVEL | C18: NEFT | E18: 6505 | F18: 84180.03
A19: 2026-07-08 | B19: KATHIRVEL UPI/KATHIRVEL/pkvel123-1@oka/UPI/CANARA BAN/655544574745/ICI4684b6b69e254d5e9691da 57f2e8e988/ PhonePe Limited | C19: UPI | D19: 250 | F19: 83930.03
A20: 2026-07-09 | B20: PhonePe Limited NEFT-YESAP61904958547-PhonePe Limited-F09 M22UYYZ10YB2URED-002261100000025- YESB0000001 sofikulisl | C20: NEFT | E20: 2985 | F20: 86915.03
A21: 2026-07-09 | B21: sofikulisl UPI/sofikulisl/sofikulislam05/UPI/INDIAN BAN/619073325859/ICI23c51785fc414b04894fef9 58a949c37/ PhonePe Limited | C21: UPI | D21: 10900 | F21: 76015.03
A22: 2026-07-10 | B22: PhonePe Limited NEFT-YESAP61915061851-PhonePe Limited-F09 M22UYYZ10YB2URED-002261100000025- YESB0000001 PANDIYAN M | C22: NEFT | E22: 9105 | F22: 85120.03
A23: 2026-07-10 | B23: PANDIYAN M UPI/PANDIYAN M/9952794361-n48/UPI/TAMILNAD M/655723115941/ICIbb0fac59da954fb7903255e30 44142bd/ PAZHE RAND | C23: UPI | D23: 40 | F23: 85080.03
A24: 2026-07-10 | B24: PAZHE RAND UPI/PAZHE RAND/paytmqr6urnlc@/UPI/YES BANK L/655703106411/ICI89b6ca961cec43129370a5b50 e0446ef/ sofikulisl | C24: UPI | D24: 23 | F24: 85057.03
A25: 2026-07-10 | B25: sofikulisl UPI/sofikulisl/sofikulislam05/enji/INDIAN BAN/655734622956/ICI2613008cb3234e169d1bc5 656b16f39d/ RAJKUMAR C | C25: UPI | D25: 10500 | F25: 74557.03
A26: 2026-07-10 | B26: RAJKUMAR C UPI/RAJKUMAR C/paytmqr72sypy@/UPI/YES BANK L/655760944716/ICI5b9f025a34564433b826a31a6 b612969/ SREENIVASA | C26: UPI | D26: 12 | F26: 74545.03
A27: 2026-07-10 | B27: SREENIVASA UPI/SREENIVASA/gpay-121906071/UPI/AXIS BANK/655736042646/ICI13763f2b02f64ae6ad76b 288a3285aea/ Pandiyan M | C27: UPI | D27: 5 | F27: 74540.03
A28: 2026-07-10 | B28: Pandiyan M UPI/Pandiyan M/paytm.s28sl0k@/UPI/YES BANK P/655723263070/ICIe12bd0e9b54d459fb27a35857 a5b7783/ PhonePe Limited | C28: UPI | D28: 50 | F28: 74490.03
A29: 2026-07-11 | B29: PhonePe Limited NEFT-YESAP61921537849-PhonePe Limited-F09 M22UYYZ10YB2URED-002261100000025- YESB0000001 JAYAPRAKAS | C29: NEFT | E29: 12600 | F29: 87090.03
A30: 2026-07-11 | B30: JAYAPRAKAS UPI/JAYAPRAKAS/paytmqr2810050/UPI/YES BANK L/655887182678/ICIc3e51031bcc34c9d9b1f09807 bcefbd3/ www.icici.bank.in Dial your Bank 1800-1080 Please call from your register | C30: UPI | D30: 20 | F30: 87070.03
A31: 2026-07-11 | B31: MADHAVAN N UPI/MADHAVAN N/gpay-122007105/UPI/AXIS BANK/619274129607/ICI4be8433fa2364910a6b27 282109f4fb8/ PhonePe Limited | C31: UPI | D31: 50 | F31: 87020.03
A32: 2026-07-12 | B32: PhonePe Limited NEFT-YESAP61935557816-PhonePe Limited-F09 M22UYYZ10YB2URED-002261100000025- YESB0000001 COIMBATORE | C32: NEFT | E32: 5510 | F32: 92530.03
A33: 2026-07-12 | B33: COIMBATORE UPI/COIMBATORE/paytmqr6rayv6@/UPI/YES BANK L/619317989381/ICI08fd9ee1d2f5452f89fb93b4d8 d139fb/ RAJKUMAR C | C33: UPI | D33: 200 | F33: 92330.03
A34: 2026-07-12 | B34: RAJKUMAR C UPI/RAJKUMAR C/paytmqr72sypy@/UPI/YES BANK L/619344588510/ICI789c0b72396647e9a9ab5e636 be69c3d/ PhonePe Limited | C34: UPI | D34: 36 | F34: 92294.03
A35: 2026-07-13 | B35: PhonePe Limited NEFT-YESAP61945012265-PhonePe Limited-F09 M22UYYZ10YB2URED-002261100000025- YESB0000001 VELU | C35: NEFT | E35: 1685 | F35: 93979.03
A36: 2026-07-13 | B36: VELU UPI/VELU/vel.reachme@ok/UPI/UNION BANK/656088659402/ICI73e3522661b342b699ed0 b784a7a7fa8/ israeljarw | C36: UPI | D36: 80 | F36: 93899.03
A37: 2026-07-13 | B37: israeljarw UPI/israeljarw/israeljarwish-/UPI/ICICI Bank/656029158365/ICIba38f460e5c545308e3a1a 2b6ce1d413/ SHRI VARI | C37: UPI | D37: 110 | F37: 93789.03
A38: 2026-07-14 | B38: SHRI VARI UPI/SHRI VARI/gpay-112408887/rv garlic/AXIS BANK/619513218584/ICI41650d4810cc425986bd5 dc26d19e400/ PhonePe Limited | C38: UPI | D38: 3250 | F38: 90539.03
A39: 2026-07-15 | B39: PhonePe Limited NEFT-YESAP61964232060-PhonePe Limited-F09 M22UYYZ10YB2URED-002261100000025- YESB0000001 PhonePe Limited | C39: NEFT | E39: 3780 | F39: 94319.03
A40: 2026-07-16 | B40: PhonePe Limited NEFT-YESAP61974911891-PhonePe Limited-F09 M22UYYZ10YB2URED-002261100000025- YESB0000001 PhonePe Limited | C40: NEFT | E40: 7610 | F40: 101929.03
A41: 2026-07-17 | B41: PhonePe Limited NEFT-YESAP61986806371-PhonePe Limited-F09 M22UYYZ10YB2URED-002261100000025- YESB0000001 PhonePe Limited | C41: NEFT | E41: 8770 | F41: 110699.03
A42: 2026-07-18 | B42: PhonePe Limited NEFT-YESAP61995120505-PhonePe Limited-F09 M22UYYZ10YB2URED-002261100000025- YESB0000001 PhonePe Limited | C42: NEFT | E42: 2620 | F42: 113319.03
A43: 2026-07-19 | B43: PhonePe Limited NEFT-YESAP62003620996-PhonePe Limited-F09 M22UYYZ10YB2URED-002261100000025- YESB0000001 PhonePe Limited | C43: NEFT | E43: 2075 | F43: 115394.03
A44: 2026-07-20 | B44: PhonePe Limited NEFT-YESAP62014503929-PhonePe Limited-F09 M22UYYZ10YB2URED-002261100000025- YESB0000001 PhonePe Limited | C44: NEFT | E44: 5955 | F44: 121349.03
A45: 2026-07-21 | B45: PhonePe Limited NEFT-YESAP62024627177-PhonePe Limited-F09 M22UYYZ10YB2URED-002261100000025- YESB0000001 hemajanani | C45: NEFT | E45: 5670 | F45: 127019.03
A46: 2026-07-21 | B46: hemajanani UPI/hemajanani/hemajananimsc-/deposit/INDIAN BAN/620273516320/ICIb67eb23821d249279ba083 0f3831ef48/ www.icici.bank.in Dial your Bank 1800-1080 Please call from your regi | C46: UPI | D46: 99000 | F46: 28019.03
A47: 2026-07-22 | B47: PhonePe Limited NEFT-YESAP62034464483-PhonePe Limited-F09 M22UYYZ10YB2URED-002261100000025- YESB0000001 PhonePe Limited | C47: NEFT | E47: 870 | F47: 28889.03
A48: 2026-07-23 | B48: PhonePe Limited NEFT-YESAP62044738039-PhonePe Limited-F09 M22UYYZ10YB2URED-002261100000025- YESB0000001 PhonePe Limited | C48: NEFT | E48: 13615 | F48: 42504.03
A49: 2026-07-24 | B49: PhonePe Limited NEFT-YESAP62054398203-PhonePe Limited-F09 M22UYYZ10YB2URED-002261100000025- YESB0000001 PhonePe Limited | C49: NEFT | E49: 21745 | F49: 64249.03
A50: 2026-07-25 | B50: PhonePe Limited NEFT-YESAP62065067114-PhonePe Limited-F09 M22UYYZ10YB2URED-002261100000025- YESB0000001 PhonePe Limited | C50: NEFT | E50: 3190 | F50: 67439.03
A51: 2026-07-26 | B51: PhonePe Limited NEFT-YESAP62073818860-PhonePe Limited-F09 M22UYYZ10YB2URED-002261100000025- YESB0000001 PhonePe Limited | C51: NEFT | E51: 3955 | F51: 71394.03
A52: 2026-07-27 | B52: PhonePe Limited NEFT-YESAP62084737272-PhonePe Limited-F09 M22UYYZ10YB2URED-002261100000025- YESB0000001 PhonePe Limited | C52: NEFT | E52: 7346 | F52: 78740.03
A53: 2026-07-28 | B53: PhonePe Limited NEFT-YESAP62094802264-PhonePe Limited-F09 M22UYYZ10YB2URED-002261100000025- YESB0000001 VISHNU GAR | C53: NEFT | E53: 7505 | F53: 86245.03
A54: 2026-07-28 | B54: VISHNU GAR UPI/VISHNU GAR/vishnu01rayakv/UPI/HDFC BANK/620987574695/ICI8cf753b21bd64182a221a e3c70cdada8/ Credit trxn | C54: UPI | D54: 50000 | F54: 36245.03
A55: 2026-07-28 | B55: Credit trxn CAM/03421HRY/CASH DEP-Other/28-07-26/7477 Credit trxn | C55: Cash Deposit | E55: 44000 | F55: 80245.03
A56: 2026-07-28 | B56: Credit trxn CAM/03421HRY/CASH DEP-Other/28-07-26/7479 Credit trxn | C56: Cash Deposit | E56: 50000 | F56: 130245.03
A57: 2026-07-28 | B57: Credit trxn CAM/03421HRY/CASH DEP-Other/28-07-26/7481 T Santhama | C57: Cash Deposit | E57: 3000 | F57: 133245.03
A58: 2026-07-28 | B58: T Santhama UPI/T Santhama/paytm.d3626309/UPI/YES BANK P/657586912132/ICIec1ff83391804e729563bd31e 88296de/ NAGARAJAN | C58: UPI | D58: 200 | F58: 133045.03
A59: 2026-07-28 | B59: NAGARAJAN BIL/NEFT/IN12620947986563/NAGARAJAN /HDFC BANK VISHNU GAR | C59: Bill/Internet transfer | D59: 80000 | F59: 53045.03
A60: 2026-07-28 | B60: VISHNU GAR UPI/VISHNU GAR/vishnu01rayakv/UPI/HDFC BANK/657538809293/ICIe5a36de0ec5d4310814bc 52e966fbf65/ NAGARAJAN | C60: UPI | D60: 49000 | F60: 4045.03
A61: 2026-07-28 | B61: NAGARAJAN MMT/IMPS/620918715347/NAGARAJAN /HDFC0002231 PhonePe Limited | C61: IMPS | D61: 1 | F61: 4044.03
A62: 2026-07-29 | B62: PhonePe Limited NEFT-YESAP62104336224-PhonePe Limited-F09 M22UYYZ10YB2URED-002261100000025- YESB0000001 PhonePe Limited | C62: NEFT | E62: 9850 | F62: 13894.03
A63: 2026-07-30 | B63: PhonePe Limited NEFT-YESAP62114799535-PhonePe Limited-F09 M22UYYZ10YB2URED-002261100000025- YESB0000001 PhonePe Limited | C63: NEFT | E63: 7295 | F63: 21189.03
A64: 2026-07-31 | B64: PhonePe Limited NEFT-YESAP62123988770-PhonePe Limited-F09 M22UYYZ10YB2URED-002261100000025- YESB0000001 www.icici.bank.in Dial your Bank 1800-1080 Please call from your registered | C64: NEFT | E64: 4565 | F64: 25754.03
A65: 2026-08-01 | B65: PhonePe Limited NEFT-YESAP62134270843-PhonePe Limited-F09 M22UYYZ10YB2URED-002261100000025- YESB0000001 PhonePe Limited | C65: NEFT | E65: 2165 | F65: 27919.03
A66: 2026-08-02 | B66: PhonePe Limited NEFT-YESAP62144194966-PhonePe Limited-F09 M22UYYZ10YB2URED-002261100000025- YESB0000001 PhonePe Limited | C66: NEFT | E66: 14295 | F66: 42214.03
A67: 2026-08-03 | B67: PhonePe Limited NEFT-YESAP62155029499-PhonePe Limited-F09 M22UYYZ10YB2URED-002261100000025- YESB0000001 NAGARAJAN | C67: NEFT | E67: 8110 | F67: 50324.03
A68: 2026-08-03 | B68: NAGARAJAN MMT/IMPS/621514265120/NAGARAJAN /HDFC0002231 PhonePe Limited | C68: IMPS | D68: 40000 | F68: 10324.03
A69: 2026-08-04 | B69: PhonePe Limited NEFT-YESAP62164484795-PhonePe Limited-F09 M22UYYZ10YB2URED-002261100000025- YESB0000001 PhonePe Limited | C69: NEFT | E69: 2635 | F69: 12959.03
A70: 2026-08-05 | B70: PhonePe Limited NEFT-YESAP62174096931-PhonePe Limited-F09 M22UYYZ10YB2URED-002261100000025- YESB0000001 PhonePe Limited | C70: NEFT | E70: 1700 | F70: 14659.03
A71: 2026-08-06 | B71: PhonePe Limited NEFT-YESAP62184577325-PhonePe Limited-F09 M22UYYZ10YB2URED-002261100000025- YESB0000001 NAGARAJAN | C71: NEFT | E71: 3802 | F71: 18461.03
A72: 2026-08-06 | B72: NAGARAJAN MMT/IMPS/621811855692/NAGARAJAN /HDFC0002231 PhonePe Limited | C72: IMPS | D72: 10000 | F72: 8461.03
A73: 2026-08-07 | B73: PhonePe Limited NEFT-YESAP62194008020-PhonePe Limited-F09 M22UYYZ10YB2URED-002261100000025- YESB0000001 AKJ TRADER | C73: NEFT | E73: 10860 | F73: 19321.03
A74: 2026-08-07 | B74: AKJ TRADER UPI/AKJ TRADER/nassarakj786@o/UPI/AXIS BANK/621909981754/ICIc72923a6b7c5457db43ad b71d02953ad/ NAGARAJAN | C74: UPI | D74: 3600 | F74: 15721.03
A75: 2026-08-07 | B75: NAGARAJAN MMT/IMPS/621915603998/NAGARAJAN /HDFC0002231 Ramesh M | C75: IMPS | D75: 10000 | F75: 5721.03
A76: 2026-08-07 | B76: Ramesh M UPI/Ramesh M/paytm.s2epecl@/UPI/YES BANK P/658586324243/ICI707f274c66f445ac9ecb5f7d5d 936d09/ Vishwa Mut | C76: UPI | D76: 140 | F76: 5581.03
A77: 2026-08-07 | B77: Vishwa Mut UPI/Vishwa Mut/q661096482@ybl/UPI/YES BANK L/658579408665/ICIea8571d687234cdd8a14c0f6b 42be79e/ Vishwa Mut | C77: UPI | D77: 225 | F77: 5356.03
A78: 2026-08-07 | B78: Vishwa Mut UPI/Vishwa Mut/q661096482@ybl/UPI/YES BANK L/658528629956/ICI0f2f9d9bdae84b59b2ab2ccc4a bc502d/ PhonePe Limited | C78: UPI | D78: 20 | F78: 5336.03
A79: 2026-08-08 | B79: PhonePe Limited NEFT-YESAP62204220465-PhonePe Limited-F09 M22UYYZ10YB2URED-002261100000025- YESB0000001 Noor Hasan | C79: NEFT | E79: 3847 | F79: 9183.03
A80: 2026-08-08 | B80: Noor Hasan UPI/Noor Hasan/paytm.s1ll34j@/UPI/YES BANK P/658607433675/ICI19b5c8f7df144b62830604172 e1316e4/ www.icici.bank.in Dial your Bank 1800-1080 Please call from your register | C80: UPI | D80: 30 | F80: 9153.03
A81: 2026-08-08 | B81: Suganya A UPI/Suganya A/paytm.s225qiv@/UPI/YES BANK P/658605832663/ICIbf966ef3ea034e3cb87f873253 32ce1f/ sriidharv | C81: UPI | D81: 30 | F81: 9123.03
A82: 2026-08-08 | B82: sriidharv UPI/sriidharv/sriidharv@okic/UPI/ICICI Bank/658692466671/ICI03520d5d51a64f18b7870d 661208f0aa/ NEW ANNAPO | C82: UPI | D82: 50 | F82: 9073.03
A83: 2026-08-08 | B83: NEW ANNAPO UPI/NEW ANNAPO/q132905451@ybl/UPI/YES BANK L/658650975973/ICIe975f315658f4937b81773f417 7cb164/ MANIMARAN | C83: UPI | D83: 60 | F83: 9013.03
A84: 2026-08-08 | B84: MANIMARAN UPI/MANIMARAN/paytmqr6do4pc@/UPI/YES BANK L/658615067263/ICI5f9fdb419ff14fc5a6669e143d9 a0da7/ KATHIRVEL | C84: UPI | D84: 30 | F84: 8983.03
A85: 2026-08-08 | B85: KATHIRVEL UPI/KATHIRVEL/pkvel123-1@oka/UPI/CANARA BAN/658636390038/ICIe045517df17e4397a482f93 4f556c45c/ BALAPRAKAS | C85: UPI | D85: 250 | F85: 8733.03
A86: 2026-08-08 | B86: BALAPRAKAS UPI/BALAPRAKAS/9361075590@ybl/UPI/CANARA BAN/622083908686/ICI055b298e53254caaa10958 b9a1d4bf6a/ PHONEPE LIMITED | C86: UPI | D86: 800 | F86: 7933.03
A87: 2026-08-09 | B87: PHONEPE LIMITED NEFT-AXNPN22104298847-PHONEPE LIMITED- PAYMENT AGGREGATOR ESCROW ACCOUNT-F09 M22UYYZ10YB2URED-922020 SHANTHI EN | C87: NEFT | E87: 6065 | F87: 13998.03
A88: 2026-08-09 | B88: SHANTHI EN UPI/SHANTHI EN/paytm.d9209839/UPI/YES BANK P/622174728606/ICIf4bf0ba6519740898ffc6faf23c 84698/ Vinoth Man | C88: UPI | D88: 300 | F88: 13698.03
A89: 2026-08-09 | B89: Vinoth Man UPI/Vinoth Man/q682511341@ybl/UPI/YES BANK L/622184136378/ICIf03f7e06203f4b9ba50b2dde47 765388/ RAJA ICE K | C89: UPI | D89: 35 | F89: 13663.03
A90: 2026-08-09 | B90: RAJA ICE K UPI/RAJA ICE K/q416698740@ybl/UPI/YES BANK L/622182834056/ICI059d0d6725e547108b37cb087 c63fcb8/ THAVLATH N | C90: UPI | D90: 20 | F90: 13643.03
A91: 2026-08-09 | B91: THAVLATH N UPI/THAVLATH N/eze0332903@cub/UPI/CITY UNION/622175334641/ICIe79ef0da4e2b4b55ba3f5 519715cace9/ SHAHJAHAN | C91: UPI | D91: 30 | F91: 13613.03
A92: 2026-08-09 | B92: SHAHJAHAN UPI/SHAHJAHAN/gpay-112643890/UPI/AXIS BANK/622195953049/ICIed141fce814a4b36838e2 aa54be6a53d/ Syed Buhar | C92: UPI | D92: 20 | F92: 13593.03
A93: 2026-08-09 | B93: Syed Buhar UPI/Syed Buhar/paytmqr5vru25@/UPI/YES BANK L/622118357514/ICI404c4c7ee5304f5682cf8544b7 42a7f3/ Absarali | C93: UPI | D93: 150 | F93: 13443.03
A94: 2026-08-09 | B94: Absarali UPI/Absarali/paytm.s1lsmmg@/UPI/YES BANK P/622183976182/ICI7f193d89128246ba966185b20 a597f53/ AROMA BAKE | C94: UPI | D94: 150 | F94: 13293.03
A95: 2026-08-09 | B95: AROMA BAKE UPI/AROMA BAKE/q653208232@ybl/UPI/YES BANK L/622196674389/ICI36454a5155b14702be351dd0 e3bcda49/ www.icici.bank.in Dial your Bank 1800-1080 Please call from your register | C95: UPI | D95: 20 | F95: 13273.03
A96: 2026-08-09 | B96: SRI SAAI B UPI/SRI SAAI B/paytm.s17nhjp@/UPI/YES BANK P/622192784919/ICI33f00d1c8d474edb86994cd80 bfe2cee/ PhonePe Limited | C96: UPI | D96: 80 | F96: 13193.03
A97: 2026-08-10 | B97: PhonePe Limited NEFT-YESAP62225061469-PhonePe Limited-F09 M22UYYZ10YB2URED-002261100000025- YESB0000001 COIMBATORE | C97: NEFT | E97: 3435 | F97: 16628.03
A98: 2026-08-10 | B98: COIMBATORE UPI/COIMBATORE/paytmqr6rayuu@/UPI/YES BANK L/658847711140/ICI8578bc9bf9244ac3be24c5f68c a8bef8/ MOHANDAS C | C98: UPI | D98: 200 | F98: 16428.03
A99: 2026-08-10 | B99: MOHANDAS C UPI/MOHANDAS C/das.samsung@yb/UPI/HDFC BANK/658894761148/ICI04529ad5f43c4e87a6304 c92903915e4/ PhonePe Limited | C99: UPI | D99: 559 | F99: 15869.03
A100: 2026-08-11 | B100: PhonePe Limited NEFT-YESAP62235056298-PhonePe Limited-F09 M22UYYZ10YB2URED-002261100000025- YESB0000001 shankarpar | C100: NEFT | E100: 3745 | F100: 19614.03
A101: 2026-08-11 | B101: shankarpar UPI/shankarpar/shankarparamu1/UPI/State Bank/658966699715/ICI7bd1b1c270054db188b69f 5ba6e39e58/ SHRI VARI | C101: UPI | D101: 500 | F101: 19114.03
...
